{
  "symbol": "LEQ26",
  "commodity": "Live Cattle",
  "month": "Aug",
  "updatedAt": "2026-07-21T10:38:54.587779-05:00",
  "rows": [
    {
      "date": "2026-07-21",
      "dailyHigh": "227.75",
      "dailyLow": "225.5",
      "dailyRange": "2.25",
      "fullAchievement": "2.825",
      "historicVol": "16.0%",
      "impliedVol": "",
      "weeklyHigh": "227.75",
      "weeklyLow": "223.675",
      "weeklyRange": "4.075",
      "sectionBreak": false,
      "dailyTarget": "2.85",
      "nextDailyTarget": "2.25",
      "dailyAchievement": "78.9%",
      "weeklyTarget": "8.95",
      "nextWeeklyTarget": "",
      "weeklyAchievement": "45.5%",
      "impliedVolTrend": "",
      "underTargetStreak": 1,
      "weeklyUnderTargetStreak": 0,
      "weeklyTrend": "up|2"
    },
    {
      "date": "2026-07-20",
      "dailyHigh": "226.85",
      "dailyLow": "223.675",
      "dailyRange": "3.175",
      "fullAchievement": "3.575",
      "historicVol": "20.2%",
      "impliedVol": "15.7%",
      "weeklyHigh": "226.85",
      "weeklyLow": "223.675",
      "weeklyRange": "3.175",
      "sectionBreak": true,
      "dailyTarget": "2.75",
      "nextDailyTarget": "2.85",
      "dailyAchievement": "115.5%",
      "weeklyTarget": "8.95",
      "nextWeeklyTarget": "",
      "weeklyAchievement": "35.5%",
      "impliedVolTrend": "",
      "underTargetStreak": 0,
      "weeklyUnderTargetStreak": 0,
      "weeklyTrend": "up|2"
    },
    {
      "date": "2026-07-17",
      "dailyHigh": "227.25",
      "dailyLow": "224.2",
      "dailyRange": "3.05",
      "fullAchievement": "3.45",
      "historicVol": "19.7%",
      "impliedVol": "15.7%",
      "weeklyHigh": "236.5",
      "weeklyLow": "224.2",
      "weeklyRange": "12.3",
      "sectionBreak": false,
      "dailyTarget": "2.875",
      "nextDailyTarget": "2.75",
      "dailyAchievement": "106.1%",
      "weeklyTarget": "6.35",
      "nextWeeklyTarget": "8.95",
      "weeklyAchievement": "193.7%",
      "impliedVolTrend": "up|4",
      "underTargetStreak": 0,
      "weeklyUnderTargetStreak": 0,
      "weeklyTrend": "up|2"
    },
    {
      "date": "2026-07-16",
      "dailyHigh": "230.5",
      "dailyLow": "226.025",
      "dailyRange": "4.475",
      "fullAchievement": "3.6",
      "historicVol": "20.3%",
      "impliedVol": "15.4%",
      "weeklyHigh": "236.5",
      "weeklyLow": "226.025",
      "weeklyRange": "10.475",
      "sectionBreak": false,
      "dailyTarget": "2.175",
      "nextDailyTarget": "2.875",
      "dailyAchievement": "205.7%",
      "weeklyTarget": "6.35",
      "nextWeeklyTarget": "",
      "weeklyAchievement": "165.0%",
      "impliedVolTrend": "up|3",
      "underTargetStreak": 0,
      "weeklyUnderTargetStreak": 0,
      "weeklyTrend": "up|2"
    },
    {
      "date": "2026-07-15",
      "dailyHigh": "232.1",
      "dailyLow": "229.25",
      "dailyRange": "2.85",
      "fullAchievement": "2.725",
      "historicVol": "15.2%",
      "impliedVol": "14.5%",
      "weeklyHigh": "236.5",
      "weeklyLow": "229.25",
      "weeklyRange": "7.25",
      "sectionBreak": false,
      "dailyTarget": "2.25",
      "nextDailyTarget": "2.175",
      "dailyAchievement": "126.7%",
      "weeklyTarget": "6.35",
      "nextWeeklyTarget": "",
      "weeklyAchievement": "114.2%",
      "impliedVolTrend": "up|2",
      "underTargetStreak": 0,
      "weeklyUnderTargetStreak": 0,
      "weeklyTrend": "up|2"
    },
    {
      "date": "2026-07-14",
      "dailyHigh": "234.225",
      "dailyLow": "231.25",
      "dailyRange": "3.475",
      "fullAchievement": "2.825",
      "historicVol": "15.7%",
      "impliedVol": "14.4%",
      "weeklyHigh": "236.5",
      "weeklyLow": "231.25",
      "weeklyRange": "5.25",
      "sectionBreak": false,
      "dailyTarget": "2.425",
      "nextDailyTarget": "2.25",
      "dailyAchievement": "143.3%",
      "weeklyTarget": "6.35",
      "nextWeeklyTarget": "",
      "weeklyAchievement": "82.7%",
      "impliedVolTrend": "up|1",
      "underTargetStreak": 0,
      "weeklyUnderTargetStreak": 0,
      "weeklyTrend": "up|2"
    },
    {
      "date": "2026-07-13",
      "dailyHigh": "236.5",
      "dailyLow": "234.625",
      "dailyRange": "1.875",
      "fullAchievement": "3.025",
      "historicVol": "16.5%",
      "impliedVol": "14.2%",
      "weeklyHigh": "236.5",
      "weeklyLow": "234.625",
      "weeklyRange": "1.875",
      "sectionBreak": true,
      "dailyTarget": "3.025",
      "nextDailyTarget": "2.425",
      "dailyAchievement": "62.0%",
      "weeklyTarget": "6.35",
      "nextWeeklyTarget": "",
      "weeklyAchievement": "29.5%",
      "impliedVolTrend": "down|1",
      "underTargetStreak": 1,
      "weeklyUnderTargetStreak": 0,
      "weeklyTrend": "up|2"
    },
    {
      "date": "2026-07-10",
      "dailyHigh": "236.075",
      "dailyLow": "232.925",
      "dailyRange": "3.15",
      "fullAchievement": "3.775",
      "historicVol": "20.6%",
      "impliedVol": "14.3%",
      "weeklyHigh": "240.55",
      "weeklyLow": "232.925",
      "weeklyRange": "7.625",
      "sectionBreak": false,
      "dailyTarget": "2.925",
      "nextDailyTarget": "3.025",
      "dailyAchievement": "107.7%",
      "weeklyTarget": "6.8",
      "nextWeeklyTarget": "6.35",
      "weeklyAchievement": "112.1%",
      "impliedVolTrend": "up|2",
      "underTargetStreak": 0,
      "weeklyUnderTargetStreak": 0,
      "weeklyTrend": "up|1"
    },
    {
      "date": "2026-07-09",
      "dailyHigh": "238.475",
      "dailyLow": "234.4",
      "dailyRange": "4.075",
      "fullAchievement": "3.65",
      "historicVol": "19.9%",
      "impliedVol": "13.1%",
      "weeklyHigh": "240.55",
      "weeklyLow": "234.375",
      "weeklyRange": "6.175",
      "sectionBreak": false,
      "dailyTarget": "2.45",
      "nextDailyTarget": "2.925",
      "dailyAchievement": "166.3%",
      "weeklyTarget": "6.8",
      "nextWeeklyTarget": "",
      "weeklyAchievement": "90.8%",
      "impliedVolTrend": "up|1",
      "underTargetStreak": 0,
      "weeklyUnderTargetStreak": 0,
      "weeklyTrend": "up|1"
    },
    {
      "date": "2026-07-08",
      "dailyHigh": "238.5",
      "dailyLow": "234.375",
      "dailyRange": "4.125",
      "fullAchievement": "3.05",
      "historicVol": "16.4%",
      "impliedVol": "12.6%",
      "weeklyHigh": "240.55",
      "weeklyLow": "234.375",
      "weeklyRange": "6.175",
      "sectionBreak": false,
      "dailyTarget": "2.425",
      "nextDailyTarget": "2.45",
      "dailyAchievement": "170.1%",
      "weeklyTarget": "6.8",
      "nextWeeklyTarget": "",
      "weeklyAchievement": "90.8%",
      "impliedVolTrend": "",
      "underTargetStreak": 0,
      "weeklyUnderTargetStreak": 0,
      "weeklyTrend": "up|1"
    },
    {
      "date": "2026-07-07",
      "dailyHigh": "239.825",
      "dailyLow": "237.05",
      "dailyRange": "2.775",
      "fullAchievement": "3.025",
      "historicVol": "16.3%",
      "impliedVol": "12.6%",
      "weeklyHigh": "240.55",
      "weeklyLow": "237.05",
      "weeklyRange": "3.5",
      "sectionBreak": false,
      "dailyTarget": "2.425",
      "nextDailyTarget": "2.425",
      "dailyAchievement": "114.4%",
      "weeklyTarget": "6.8",
      "nextWeeklyTarget": "",
      "weeklyAchievement": "51.5%",
      "impliedVolTrend": "down|2",
      "underTargetStreak": 0,
      "weeklyUnderTargetStreak": 0,
      "weeklyTrend": "up|1"
    },
    {
      "date": "2026-07-06",
      "dailyHigh": "240.55",
      "dailyLow": "238.3",
      "dailyRange": "2.25",
      "fullAchievement": "3.025",
      "historicVol": "16.2%",
      "impliedVol": "12.9%",
      "weeklyHigh": "240.55",
      "weeklyLow": "238.3",
      "weeklyRange": "2.25",
      "sectionBreak": true,
      "dailyTarget": "2.75",
      "nextDailyTarget": "2.425",
      "dailyAchievement": "81.8%",
      "weeklyTarget": "6.8",
      "nextWeeklyTarget": "",
      "weeklyAchievement": "33.1%",
      "impliedVolTrend": "down|1",
      "underTargetStreak": 1,
      "weeklyUnderTargetStreak": 0,
      "weeklyTrend": "up|1"
    },
    {
      "date": "2026-07-02",
      "dailyHigh": "243",
      "dailyLow": "238.925",
      "dailyRange": "4.075",
      "fullAchievement": "3.45",
      "historicVol": "18.5%",
      "impliedVol": "14.5%",
      "weeklyHigh": "245.825",
      "weeklyLow": "238.925",
      "weeklyRange": "6.9",
      "sectionBreak": false,
      "dailyTarget": "2.55",
      "nextDailyTarget": "2.75",
      "dailyAchievement": "159.8%",
      "weeklyTarget": "7.2",
      "nextWeeklyTarget": "6.8",
      "weeklyAchievement": "95.8%",
      "impliedVolTrend": "up|1",
      "underTargetStreak": 0,
      "weeklyUnderTargetStreak": 0,
      "weeklyTrend": "down|2"
    },
    {
      "date": "2026-07-01",
      "dailyHigh": "243.75",
      "dailyLow": "241",
      "dailyRange": "2.75",
      "fullAchievement": "3.175",
      "historicVol": "16.8%",
      "impliedVol": "14.1%",
      "weeklyHigh": "245.825",
      "weeklyLow": "240.925",
      "weeklyRange": "4.9",
      "sectionBreak": false,
      "dailyTarget": "2.275",
      "nextDailyTarget": "2.55",
      "dailyAchievement": "120.9%",
      "weeklyTarget": "7.2",
      "nextWeeklyTarget": "",
      "weeklyAchievement": "68.1%",
      "impliedVolTrend": "down|2",
      "underTargetStreak": 0,
      "weeklyUnderTargetStreak": 0,
      "weeklyTrend": "down|2"
    },
    {
      "date": "2026-06-30",
      "dailyHigh": "244.475",
      "dailyLow": "240.925",
      "dailyRange": "3.55",
      "fullAchievement": "2.85",
      "historicVol": "15.0%",
      "impliedVol": "14.4%",
      "weeklyHigh": "245.825",
      "weeklyLow": "240.925",
      "weeklyRange": "4.9",
      "sectionBreak": false,
      "dailyTarget": "2.05",
      "nextDailyTarget": "2.275",
      "dailyAchievement": "173.2%",
      "weeklyTarget": "7.2",
      "nextWeeklyTarget": "",
      "weeklyAchievement": "68.1%",
      "impliedVolTrend": "down|1",
      "underTargetStreak": 0,
      "weeklyUnderTargetStreak": 0,
      "weeklyTrend": "down|2"
    },
    {
      "date": "2026-06-29",
      "dailyHigh": "245.6",
      "dailyLow": "242.6",
      "dailyRange": "3.225",
      "fullAchievement": "2.575",
      "historicVol": "13.6%",
      "impliedVol": "14.7%",
      "weeklyHigh": "245.825",
      "weeklyLow": "242.6",
      "weeklyRange": "3.225",
      "sectionBreak": true,
      "dailyTarget": "1.85",
      "nextDailyTarget": "2.05",
      "dailyAchievement": "174.3%",
      "weeklyTarget": "7.2",
      "nextWeeklyTarget": "",
      "weeklyAchievement": "44.8%",
      "impliedVolTrend": "up|3",
      "underTargetStreak": 0,
      "weeklyUnderTargetStreak": 0,
      "weeklyTrend": "down|2"
    },
    {
      "date": "2026-06-26",
      "dailyHigh": "247.25",
      "dailyLow": "245.5",
      "dailyRange": "1.75",
      "fullAchievement": "2.3",
      "historicVol": "12.0%",
      "impliedVol": "14.6%",
      "weeklyHigh": "250",
      "weeklyLow": "245.475",
      "weeklyRange": "4.525",
      "sectionBreak": false,
      "dailyTarget": "1.95",
      "nextDailyTarget": "1.85",
      "dailyAchievement": "89.7%",
      "weeklyTarget": "9.425",
      "nextWeeklyTarget": "7.2",
      "weeklyAchievement": "48.0%",
      "impliedVolTrend": "up|2",
      "underTargetStreak": 1,
      "weeklyUnderTargetStreak": 0,
      "weeklyTrend": "down|1"
    },
    {
      "date": "2026-06-25",
      "dailyHigh": "248.4",
      "dailyLow": "245.625",
      "dailyRange": "2.775",
      "fullAchievement": "2.425",
      "historicVol": "12.5%",
      "impliedVol": "14.1%",
      "weeklyHigh": "250",
      "weeklyLow": "245.475",
      "weeklyRange": "4.525",
      "sectionBreak": false,
      "dailyTarget": "2.25",
      "nextDailyTarget": "1.95",
      "dailyAchievement": "123.3%",
      "weeklyTarget": "9.425",
      "nextWeeklyTarget": "",
      "weeklyAchievement": "48.0%",
      "impliedVolTrend": "up|1",
      "underTargetStreak": 0,
      "weeklyUnderTargetStreak": 0,
      "weeklyTrend": "down|1"
    },
    {
      "date": "2026-06-24",
      "dailyHigh": "247.9",
      "dailyLow": "245.5",
      "dailyRange": "2.4",
      "fullAchievement": "2.8",
      "historicVol": "14.5%",
      "impliedVol": "14.0%",
      "weeklyHigh": "250",
      "weeklyLow": "245.475",
      "weeklyRange": "4.525",
      "sectionBreak": false,
      "dailyTarget": "2.425",
      "nextDailyTarget": "2.25",
      "dailyAchievement": "99.0%",
      "weeklyTarget": "9.425",
      "nextWeeklyTarget": "",
      "weeklyAchievement": "48.0%",
      "impliedVolTrend": "down|1",
      "underTargetStreak": 2,
      "weeklyUnderTargetStreak": 0,
      "weeklyTrend": "down|1"
    },
    {
      "date": "2026-06-23",
      "dailyHigh": "247.55",
      "dailyLow": "245.475",
      "dailyRange": "2.075",
      "fullAchievement": "3.025",
      "historicVol": "15.7%",
      "impliedVol": "14.6%",
      "weeklyHigh": "250",
      "weeklyLow": "245.475",
      "weeklyRange": "4.525",
      "sectionBreak": false,
      "dailyTarget": "2.375",
      "nextDailyTarget": "2.425",
      "dailyAchievement": "87.4%",
      "weeklyTarget": "9.425",
      "nextWeeklyTarget": "",
      "weeklyAchievement": "48.0%",
      "impliedVolTrend": "",
      "underTargetStreak": 1,
      "weeklyUnderTargetStreak": 0,
      "weeklyTrend": "down|1"
    },
    {
      "date": "2026-06-22",
      "dailyHigh": "250",
      "dailyLow": "246.1",
      "dailyRange": "3.9",
      "fullAchievement": "2.975",
      "historicVol": "15.4%",
      "impliedVol": "14.6%",
      "weeklyHigh": "250",
      "weeklyLow": "246.1",
      "weeklyRange": "3.9",
      "sectionBreak": true,
      "dailyTarget": "3.075",
      "nextDailyTarget": "2.375",
      "dailyAchievement": "126.8%",
      "weeklyTarget": "9.425",
      "nextWeeklyTarget": "",
      "weeklyAchievement": "41.4%",
      "impliedVolTrend": "",
      "underTargetStreak": 0,
      "weeklyUnderTargetStreak": 0,
      "weeklyTrend": "down|1"
    },
    {
      "date": "2026-06-18",
      "dailyHigh": "248.875",
      "dailyLow": "245.775",
      "dailyRange": "3.1",
      "fullAchievement": "3.85",
      "historicVol": "20.0%",
      "impliedVol": "14.6%",
      "weeklyHigh": "249.85",
      "weeklyLow": "240.9",
      "weeklyRange": "8.95",
      "sectionBreak": false,
      "dailyTarget": "2.95",
      "nextDailyTarget": "3.075",
      "dailyAchievement": "105.1%",
      "weeklyTarget": "8.5",
      "nextWeeklyTarget": "9.425",
      "weeklyAchievement": "105.3%",
      "impliedVolTrend": "up|1",
      "underTargetStreak": 0,
      "weeklyUnderTargetStreak": 0,
      "weeklyTrend": "up|1"
    },
    {
      "date": "2026-06-17",
      "dailyHigh": "249.85",
      "dailyLow": "247.9",
      "dailyRange": "1.95",
      "fullAchievement": "3.675",
      "historicVol": "18.9%",
      "impliedVol": "13.9%",
      "weeklyHigh": "249.85",
      "weeklyLow": "240.9",
      "weeklyRange": "8.95",
      "sectionBreak": false,
      "dailyTarget": "3.65",
      "nextDailyTarget": "2.95",
      "dailyAchievement": "53.4%",
      "weeklyTarget": "8.5",
      "nextWeeklyTarget": "",
      "weeklyAchievement": "105.3%",
      "impliedVolTrend": "down|2",
      "underTargetStreak": 1,
      "weeklyUnderTargetStreak": 0,
      "weeklyTrend": "up|1"
    },
    {
      "date": "2026-06-16",
      "dailyHigh": "249.45",
      "dailyLow": "242.95",
      "dailyRange": "6.5",
      "fullAchievement": "4.55",
      "historicVol": "23.3%",
      "impliedVol": "14.2%",
      "weeklyHigh": "249.45",
      "weeklyLow": "240.9",
      "weeklyRange": "8.55",
      "sectionBreak": false,
      "dailyTarget": "2.625",
      "nextDailyTarget": "3.65",
      "dailyAchievement": "247.6%",
      "weeklyTarget": "8.5",
      "nextWeeklyTarget": "",
      "weeklyAchievement": "100.6%",
      "impliedVolTrend": "down|1",
      "underTargetStreak": 0,
      "weeklyUnderTargetStreak": 0,
      "weeklyTrend": "up|1"
    },
    {
      "date": "2026-06-15",
      "dailyHigh": "243.45",
      "dailyLow": "240.9",
      "dailyRange": "2.55",
      "fullAchievement": "3.275",
      "historicVol": "17.2%",
      "impliedVol": "14.8%",
      "weeklyHigh": "243.45",
      "weeklyLow": "240.9",
      "weeklyRange": "2.55",
      "sectionBreak": true,
      "dailyTarget": "2.85",
      "nextDailyTarget": "2.625",
      "dailyAchievement": "89.5%",
      "weeklyTarget": "8.5",
      "nextWeeklyTarget": "",
      "weeklyAchievement": "30.0%",
      "impliedVolTrend": "",
      "underTargetStreak": 1,
      "weeklyUnderTargetStreak": 0,
      "weeklyTrend": "up|1"
    },
    {
      "date": "2026-06-12",
      "dailyHigh": "243.125",
      "dailyLow": "238.55",
      "dailyRange": "4.575",
      "fullAchievement": "3.55",
      "historicVol": "18.8%",
      "impliedVol": "14.8%",
      "weeklyHigh": "243.25",
      "weeklyLow": "235.15",
      "weeklyRange": "8.1",
      "sectionBreak": false,
      "dailyTarget": "2.925",
      "nextDailyTarget": "2.85",
      "dailyAchievement": "156.4%",
      "weeklyTarget": "10.175",
      "nextWeeklyTarget": "8.5",
      "weeklyAchievement": "79.6%",
      "impliedVolTrend": "",
      "underTargetStreak": 0,
      "weeklyUnderTargetStreak": 0,
      "weeklyTrend": "down|1"
    },
    {
      "date": "2026-06-11",
      "dailyHigh": "243.25",
      "dailyLow": "240.55",
      "dailyRange": "2.7",
      "fullAchievement": "3.65",
      "historicVol": "19.2%",
      "impliedVol": "14.8%",
      "weeklyHigh": "243.25",
      "weeklyLow": "235.15",
      "weeklyRange": "8.1",
      "sectionBreak": false,
      "dailyTarget": "4.05",
      "nextDailyTarget": "2.925",
      "dailyAchievement": "66.7%",
      "weeklyTarget": "10.175",
      "nextWeeklyTarget": "",
      "weeklyAchievement": "79.6%",
      "impliedVolTrend": "down|3",
      "underTargetStreak": 3,
      "weeklyUnderTargetStreak": 0,
      "weeklyTrend": "down|1"
    },
    {
      "date": "2026-06-10",
      "dailyHigh": "242.75",
      "dailyLow": "239.375",
      "dailyRange": "3.375",
      "fullAchievement": "5.075",
      "historicVol": "26.9%",
      "impliedVol": "15.0%",
      "weeklyHigh": "243.25",
      "weeklyLow": "235.15",
      "weeklyRange": "8.1",
      "sectionBreak": false,
      "dailyTarget": "4.35",
      "nextDailyTarget": "4.05",
      "dailyAchievement": "77.6%",
      "weeklyTarget": "10.175",
      "nextWeeklyTarget": "",
      "weeklyAchievement": "79.6%",
      "impliedVolTrend": "down|2",
      "underTargetStreak": 2,
      "weeklyUnderTargetStreak": 0,
      "weeklyTrend": "down|1"
    },
    {
      "date": "2026-06-09",
      "dailyHigh": "240",
      "dailyLow": "235.15",
      "dailyRange": "4.85",
      "fullAchievement": "5.425",
      "historicVol": "29.0%",
      "impliedVol": "16.1%",
      "weeklyHigh": "243.25",
      "weeklyLow": "235.15",
      "weeklyRange": "8.1",
      "sectionBreak": false,
      "dailyTarget": "5.25",
      "nextDailyTarget": "4.35",
      "dailyAchievement": "92.4%",
      "weeklyTarget": "10.175",
      "nextWeeklyTarget": "",
      "weeklyAchievement": "79.6%",
      "impliedVolTrend": "down|1",
      "underTargetStreak": 1,
      "weeklyUnderTargetStreak": 0,
      "weeklyTrend": "down|1"
    },
    {
      "date": "2026-06-08",
      "dailyHigh": "243.25",
      "dailyLow": "236.25",
      "dailyRange": "7",
      "fullAchievement": "6.575",
      "historicVol": "35.6%",
      "impliedVol": "16.2%",
      "weeklyHigh": "243.25",
      "weeklyLow": "236.25",
      "weeklyRange": "7",
      "sectionBreak": true,
      "dailyTarget": "4.7",
      "nextDailyTarget": "5.25",
      "dailyAchievement": "148.9%",
      "weeklyTarget": "10.175",
      "nextWeeklyTarget": "",
      "weeklyAchievement": "68.8%",
      "impliedVolTrend": "up|1",
      "underTargetStreak": 0,
      "weeklyUnderTargetStreak": 0,
      "weeklyTrend": "down|1"
    },
    {
      "date": "2026-06-05",
      "dailyHigh": "245.225",
      "dailyLow": "240.8",
      "dailyRange": "4.425",
      "fullAchievement": "5.875",
      "historicVol": "31.1%",
      "impliedVol": "15.7%",
      "weeklyHigh": "245.225",
      "weeklyLow": "233.975",
      "weeklyRange": "11.25",
      "sectionBreak": false,
      "dailyTarget": "4.45",
      "nextDailyTarget": "4.7",
      "dailyAchievement": "99.4%",
      "weeklyTarget": "9.475",
      "nextWeeklyTarget": "10.175",
      "weeklyAchievement": "118.7%",
      "impliedVolTrend": "",
      "underTargetStreak": 1,
      "weeklyUnderTargetStreak": 0,
      "weeklyTrend": "up|1"
    },
    {
      "date": "2026-06-04",
      "dailyHigh": "242.3",
      "dailyLow": "233.975",
      "dailyRange": "8.325",
      "fullAchievement": "5.575",
      "historicVol": "29.6%",
      "impliedVol": "",
      "weeklyHigh": "242.3",
      "weeklyLow": "233.975",
      "weeklyRange": "8.325",
      "sectionBreak": false,
      "dailyTarget": "2.9",
      "nextDailyTarget": "4.45",
      "dailyAchievement": "287.1%",
      "weeklyTarget": "9.475",
      "nextWeeklyTarget": "",
      "weeklyAchievement": "87.9%",
      "impliedVolTrend": "",
      "underTargetStreak": 0,
      "weeklyUnderTargetStreak": 0,
      "weeklyTrend": "up|1"
    },
    {
      "date": "2026-06-03",
      "dailyHigh": "240.225",
      "dailyLow": "235.375",
      "dailyRange": "4.85",
      "fullAchievement": "3.625",
      "historicVol": "19.6%",
      "impliedVol": "",
      "weeklyHigh": "241.4",
      "weeklyLow": "235.375",
      "weeklyRange": "6.025",
      "sectionBreak": false,
      "dailyTarget": "2.5",
      "nextDailyTarget": "2.9",
      "dailyAchievement": "194.0%",
      "weeklyTarget": "9.475",
      "nextWeeklyTarget": "",
      "weeklyAchievement": "63.6%",
      "impliedVolTrend": "",
      "underTargetStreak": 0,
      "weeklyUnderTargetStreak": 0,
      "weeklyTrend": "up|1"
    },
    {
      "date": "2026-06-02",
      "dailyHigh": "240.425",
      "dailyLow": "237.025",
      "dailyRange": "3.575",
      "fullAchievement": "3.125",
      "historicVol": "16.7%",
      "impliedVol": "",
      "weeklyHigh": "241.4",
      "weeklyLow": "237.025",
      "weeklyRange": "4.375",
      "sectionBreak": false,
      "dailyTarget": "2.15",
      "nextDailyTarget": "2.5",
      "dailyAchievement": "166.3%",
      "weeklyTarget": "9.475",
      "nextWeeklyTarget": "",
      "weeklyAchievement": "46.2%",
      "impliedVolTrend": "",
      "underTargetStreak": 0,
      "weeklyUnderTargetStreak": 0,
      "weeklyTrend": "up|1"
    },
    {
      "date": "2026-06-01",
      "dailyHigh": "241.4",
      "dailyLow": "238.925",
      "dailyRange": "2.475",
      "fullAchievement": "2.7",
      "historicVol": "14.4%",
      "impliedVol": "",
      "weeklyHigh": "241.4",
      "weeklyLow": "238.925",
      "weeklyRange": "2.475",
      "sectionBreak": true,
      "dailyTarget": "2.75",
      "nextDailyTarget": "2.15",
      "dailyAchievement": "90.0%",
      "weeklyTarget": "9.475",
      "nextWeeklyTarget": "",
      "weeklyAchievement": "26.1%",
      "impliedVolTrend": "",
      "underTargetStreak": 1,
      "weeklyUnderTargetStreak": 0,
      "weeklyTrend": "up|1"
    },
    {
      "date": "2026-05-29",
      "dailyHigh": "241.925",
      "dailyLow": "238.6",
      "dailyRange": "3.325",
      "fullAchievement": "3.45",
      "historicVol": "18.5%",
      "impliedVol": "",
      "weeklyHigh": "243.875",
      "weeklyLow": "237.75",
      "weeklyRange": "6.125",
      "sectionBreak": false,
      "dailyTarget": "3.05",
      "nextDailyTarget": "2.75",
      "dailyAchievement": "109.0%",
      "weeklyTarget": "10.05",
      "nextWeeklyTarget": "9.475",
      "weeklyAchievement": "60.9%",
      "impliedVolTrend": "",
      "underTargetStreak": 0,
      "weeklyUnderTargetStreak": 0,
      "weeklyTrend": "down|1"
    },
    {
      "date": "2026-05-28",
      "dailyHigh": "243.225",
      "dailyLow": "240.925",
      "dailyRange": "2.3",
      "fullAchievement": "3.8",
      "historicVol": "20.2%",
      "impliedVol": "",
      "weeklyHigh": "243.875",
      "weeklyLow": "237.75",
      "weeklyRange": "6.125",
      "sectionBreak": false,
      "dailyTarget": "3.55",
      "nextDailyTarget": "3.05",
      "dailyAchievement": "64.8%",
      "weeklyTarget": "10.05",
      "nextWeeklyTarget": "",
      "weeklyAchievement": "60.9%",
      "impliedVolTrend": "",
      "underTargetStreak": 1,
      "weeklyUnderTargetStreak": 0,
      "weeklyTrend": "down|1"
    },
    {
      "date": "2026-05-27",
      "dailyHigh": "243.875",
      "dailyLow": "239.425",
      "dailyRange": "4.725",
      "fullAchievement": "4.425",
      "historicVol": "23.4%",
      "impliedVol": "",
      "weeklyHigh": "243.875",
      "weeklyLow": "237.75",
      "weeklyRange": "6.125",
      "sectionBreak": false,
      "dailyTarget": "4.075",
      "nextDailyTarget": "3.55",
      "dailyAchievement": "116.0%",
      "weeklyTarget": "10.05",
      "nextWeeklyTarget": "",
      "weeklyAchievement": "60.9%",
      "impliedVolTrend": "",
      "underTargetStreak": 0,
      "weeklyUnderTargetStreak": 0,
      "weeklyTrend": "down|1"
    },
    {
      "date": "2026-05-26",
      "dailyHigh": "242.15",
      "dailyLow": "237.75",
      "dailyRange": "4.4",
      "fullAchievement": "5.1",
      "historicVol": "27.3%",
      "impliedVol": "",
      "weeklyHigh": "242.15",
      "weeklyLow": "237.75",
      "weeklyRange": "4.4",
      "sectionBreak": true,
      "dailyTarget": "4.15",
      "nextDailyTarget": "4.075",
      "dailyAchievement": "106.0%",
      "weeklyTarget": "10.05",
      "nextWeeklyTarget": "",
      "weeklyAchievement": "43.8%",
      "impliedVolTrend": "",
      "underTargetStreak": 0,
      "weeklyUnderTargetStreak": 0,
      "weeklyTrend": "down|1"
    },
    {
      "date": "2026-05-22",
      "dailyHigh": "240.975",
      "dailyLow": "236.825",
      "dailyRange": "4.15",
      "fullAchievement": "5.2",
      "historicVol": "27.8%",
      "impliedVol": "",
      "weeklyHigh": "249.975",
      "weeklyLow": "236.825",
      "weeklyRange": "13.15",
      "sectionBreak": false,
      "dailyTarget": "3.6",
      "nextDailyTarget": "4.15",
      "dailyAchievement": "115.3%",
      "weeklyTarget": "9",
      "nextWeeklyTarget": "10.05",
      "weeklyAchievement": "146.1%",
      "impliedVolTrend": "",
      "underTargetStreak": 0,
      "weeklyUnderTargetStreak": 0,
      "weeklyTrend": "up|2"
    },
    {
      "date": "2026-05-21",
      "dailyHigh": "245.5",
      "dailyLow": "238.75",
      "dailyRange": "6.75",
      "fullAchievement": "4.5",
      "historicVol": "24.1%",
      "impliedVol": "",
      "weeklyHigh": "249.975",
      "weeklyLow": "238.75",
      "weeklyRange": "11.225",
      "sectionBreak": false,
      "dailyTarget": "2.65",
      "nextDailyTarget": "3.6",
      "dailyAchievement": "254.7%",
      "weeklyTarget": "9",
      "nextWeeklyTarget": "",
      "weeklyAchievement": "124.7%",
      "impliedVolTrend": "",
      "underTargetStreak": 0,
      "weeklyUnderTargetStreak": 0,
      "weeklyTrend": "up|2"
    },
    {
      "date": "2026-05-20",
      "dailyHigh": "247.425",
      "dailyLow": "242.725",
      "dailyRange": "4.7",
      "fullAchievement": "3.325",
      "historicVol": "17.3%",
      "impliedVol": "",
      "weeklyHigh": "249.975",
      "weeklyLow": "242.725",
      "weeklyRange": "7.25",
      "sectionBreak": false,
      "dailyTarget": "2.15",
      "nextDailyTarget": "2.65",
      "dailyAchievement": "218.6%",
      "weeklyTarget": "9",
      "nextWeeklyTarget": "",
      "weeklyAchievement": "80.6%",
      "impliedVolTrend": "",
      "underTargetStreak": 0,
      "weeklyUnderTargetStreak": 0,
      "weeklyTrend": "up|2"
    },
    {
      "date": "2026-05-19",
      "dailyHigh": "248.35",
      "dailyLow": "246.275",
      "dailyRange": "2.075",
      "fullAchievement": "2.7",
      "historicVol": "14.0%",
      "impliedVol": "",
      "weeklyHigh": "249.975",
      "weeklyLow": "246.275",
      "weeklyRange": "3.7",
      "sectionBreak": false,
      "dailyTarget": "2.45",
      "nextDailyTarget": "2.15",
      "dailyAchievement": "84.7%",
      "weeklyTarget": "9",
      "nextWeeklyTarget": "",
      "weeklyAchievement": "41.1%",
      "impliedVolTrend": "",
      "underTargetStreak": 4,
      "weeklyUnderTargetStreak": 0,
      "weeklyTrend": "up|2"
    },
    {
      "date": "2026-05-18",
      "dailyHigh": "249.975",
      "dailyLow": "246.8",
      "dailyRange": "3.175",
      "fullAchievement": "3.075",
      "historicVol": "15.9%",
      "impliedVol": "",
      "weeklyHigh": "249.975",
      "weeklyLow": "246.8",
      "weeklyRange": "3.175",
      "sectionBreak": true,
      "dailyTarget": "3.475",
      "nextDailyTarget": "2.45",
      "dailyAchievement": "91.4%",
      "weeklyTarget": "9",
      "nextWeeklyTarget": "",
      "weeklyAchievement": "35.3%",
      "impliedVolTrend": "",
      "underTargetStreak": 3,
      "weeklyUnderTargetStreak": 0,
      "weeklyTrend": "up|2"
    },
    {
      "date": "2026-05-15",
      "dailyHigh": "248.375",
      "dailyLow": "245.525",
      "dailyRange": "2.85",
      "fullAchievement": "4.35",
      "historicVol": "22.5%",
      "impliedVol": "",
      "weeklyHigh": "249.025",
      "weeklyLow": "239.9",
      "weeklyRange": "9.125",
      "sectionBreak": false,
      "dailyTarget": "4.45",
      "nextDailyTarget": "3.475",
      "dailyAchievement": "64.0%",
      "weeklyTarget": "8.45",
      "nextWeeklyTarget": "9",
      "weeklyAchievement": "108.0%",
      "impliedVolTrend": "",
      "underTargetStreak": 2,
      "weeklyUnderTargetStreak": 0,
      "weeklyTrend": "up|1"
    },
    {
      "date": "2026-05-14",
      "dailyHigh": "249.025",
      "dailyLow": "245.85",
      "dailyRange": "3.175",
      "fullAchievement": "5.55",
      "historicVol": "28.8%",
      "impliedVol": "",
      "weeklyHigh": "249.025",
      "weeklyLow": "239.9",
      "weeklyRange": "9.125",
      "sectionBreak": false,
      "dailyTarget": "5.475",
      "nextDailyTarget": "4.45",
      "dailyAchievement": "58.0%",
      "weeklyTarget": "8.45",
      "nextWeeklyTarget": "",
      "weeklyAchievement": "108.0%",
      "impliedVolTrend": "",
      "underTargetStreak": 1,
      "weeklyUnderTargetStreak": 0,
      "weeklyTrend": "up|1"
    },
    {
      "date": "2026-05-13",
      "dailyHigh": "247.575",
      "dailyLow": "240.525",
      "dailyRange": "7.05",
      "fullAchievement": "6.85",
      "historicVol": "35.6%",
      "impliedVol": "",
      "weeklyHigh": "247.575",
      "weeklyLow": "239.9",
      "weeklyRange": "7.675",
      "sectionBreak": false,
      "dailyTarget": "5.025",
      "nextDailyTarget": "5.475",
      "dailyAchievement": "140.3%",
      "weeklyTarget": "8.45",
      "nextWeeklyTarget": "",
      "weeklyAchievement": "90.8%",
      "impliedVolTrend": "",
      "underTargetStreak": 0,
      "weeklyUnderTargetStreak": 0,
      "weeklyTrend": "up|1"
    },
    {
      "date": "2026-05-12",
      "dailyHigh": "247.15",
      "dailyLow": "240.75",
      "dailyRange": "6.4",
      "fullAchievement": "6.275",
      "historicVol": "33.4%",
      "impliedVol": "",
      "weeklyHigh": "247.15",
      "weeklyLow": "239.9",
      "weeklyRange": "7.25",
      "sectionBreak": false,
      "dailyTarget": "5.125",
      "nextDailyTarget": "5.025",
      "dailyAchievement": "124.9%",
      "weeklyTarget": "8.45",
      "nextWeeklyTarget": "",
      "weeklyAchievement": "85.8%",
      "impliedVolTrend": "",
      "underTargetStreak": 0,
      "weeklyUnderTargetStreak": 0,
      "weeklyTrend": "up|1"
    },
    {
      "date": "2026-05-11",
      "dailyHigh": "247",
      "dailyLow": "239.9",
      "dailyRange": "7.1",
      "fullAchievement": "6.4",
      "historicVol": "33.7%",
      "impliedVol": "",
      "weeklyHigh": "247",
      "weeklyLow": "239.9",
      "weeklyRange": "7.1",
      "sectionBreak": true,
      "dailyTarget": "3.775",
      "nextDailyTarget": "5.125",
      "dailyAchievement": "188.1%",
      "weeklyTarget": "8.45",
      "nextWeeklyTarget": "",
      "weeklyAchievement": "84.0%",
      "impliedVolTrend": "",
      "underTargetStreak": 0,
      "weeklyUnderTargetStreak": 0,
      "weeklyTrend": "up|1"
    },
    {
      "date": "2026-05-08",
      "dailyHigh": "249.3",
      "dailyLow": "243.95",
      "dailyRange": "5.35",
      "fullAchievement": "4.725",
      "historicVol": "24.7%",
      "impliedVol": "",
      "weeklyHigh": "250",
      "weeklyLow": "242.125",
      "weeklyRange": "7.875",
      "sectionBreak": false,
      "dailyTarget": "3.1",
      "nextDailyTarget": "3.775",
      "dailyAchievement": "172.6%",
      "weeklyTarget": "8.8",
      "nextWeeklyTarget": "8.45",
      "weeklyAchievement": "89.5%",
      "impliedVolTrend": "",
      "underTargetStreak": 0,
      "weeklyUnderTargetStreak": 0,
      "weeklyTrend": "down|1"
    },
    {
      "date": "2026-05-07",
      "dailyHigh": "248.625",
      "dailyLow": "242.125",
      "dailyRange": "6.775",
      "fullAchievement": "3.875",
      "historicVol": "20.1%",
      "impliedVol": "",
      "weeklyHigh": "250",
      "weeklyLow": "242.125",
      "weeklyRange": "7.875",
      "sectionBreak": false,
      "dailyTarget": "2.45",
      "nextDailyTarget": "3.1",
      "dailyAchievement": "276.5%",
      "weeklyTarget": "8.8",
      "nextWeeklyTarget": "",
      "weeklyAchievement": "89.5%",
      "impliedVolTrend": "",
      "underTargetStreak": 0,
      "weeklyUnderTargetStreak": 0,
      "weeklyTrend": "down|1"
    },
    {
      "date": "2026-05-06",
      "dailyHigh": "250",
      "dailyLow": "247.975",
      "dailyRange": "2.025",
      "fullAchievement": "3.05",
      "historicVol": "15.7%",
      "impliedVol": "",
      "weeklyHigh": "250",
      "weeklyLow": "243.95",
      "weeklyRange": "6.05",
      "sectionBreak": false,
      "dailyTarget": "2.975",
      "nextDailyTarget": "2.45",
      "dailyAchievement": "68.1%",
      "weeklyTarget": "8.8",
      "nextWeeklyTarget": "",
      "weeklyAchievement": "68.7%",
      "impliedVolTrend": "",
      "underTargetStreak": 1,
      "weeklyUnderTargetStreak": 0,
      "weeklyTrend": "down|1"
    },
    {
      "date": "2026-05-05",
      "dailyHigh": "248.975",
      "dailyLow": "246.65",
      "dailyRange": "2.8",
      "fullAchievement": "3.725",
      "historicVol": "19.2%",
      "impliedVol": "",
      "weeklyHigh": "248.975",
      "weeklyLow": "243.95",
      "weeklyRange": "5.025",
      "sectionBreak": false,
      "dailyTarget": "2.7",
      "nextDailyTarget": "2.975",
      "dailyAchievement": "103.7%",
      "weeklyTarget": "8.8",
      "nextWeeklyTarget": "",
      "weeklyAchievement": "57.1%",
      "impliedVolTrend": "",
      "underTargetStreak": 0,
      "weeklyUnderTargetStreak": 0,
      "weeklyTrend": "down|1"
    },
    {
      "date": "2026-05-04",
      "dailyHigh": "248.275",
      "dailyLow": "243.95",
      "dailyRange": "4.325",
      "fullAchievement": "3.375",
      "historicVol": "17.5%",
      "impliedVol": "",
      "weeklyHigh": "248.275",
      "weeklyLow": "243.95",
      "weeklyRange": "4.325",
      "sectionBreak": true,
      "dailyTarget": "2.225",
      "nextDailyTarget": "2.7",
      "dailyAchievement": "194.4%",
      "weeklyTarget": "8.8",
      "nextWeeklyTarget": "",
      "weeklyAchievement": "49.1%",
      "impliedVolTrend": "",
      "underTargetStreak": 0,
      "weeklyUnderTargetStreak": 0,
      "weeklyTrend": "down|1"
    },
    {
      "date": "2026-05-01",
      "dailyHigh": "251.65",
      "dailyLow": "247.6",
      "dailyRange": "4.05",
      "fullAchievement": "2.775",
      "historicVol": "14.4%",
      "impliedVol": "",
      "weeklyHigh": "251.65",
      "weeklyLow": "241.65",
      "weeklyRange": "10",
      "sectionBreak": false,
      "dailyTarget": "2.3",
      "nextDailyTarget": "2.225",
      "dailyAchievement": "176.1%",
      "weeklyTarget": "6.975",
      "nextWeeklyTarget": "8.8",
      "weeklyAchievement": "143.4%",
      "impliedVolTrend": "",
      "underTargetStreak": 0,
      "weeklyUnderTargetStreak": 0,
      "weeklyTrend": "up|3"
    },
    {
      "date": "2026-04-30",
      "dailyHigh": "250.075",
      "dailyLow": "248.35",
      "dailyRange": "1.725",
      "fullAchievement": "2.875",
      "historicVol": "14.8%",
      "impliedVol": "",
      "weeklyHigh": "251.2",
      "weeklyLow": "241.65",
      "weeklyRange": "9.55",
      "sectionBreak": false,
      "dailyTarget": "2.925",
      "nextDailyTarget": "2.3",
      "dailyAchievement": "59.0%",
      "weeklyTarget": "6.975",
      "nextWeeklyTarget": "",
      "weeklyAchievement": "136.9%",
      "impliedVolTrend": "",
      "underTargetStreak": 2,
      "weeklyUnderTargetStreak": 0,
      "weeklyTrend": "up|3"
    },
    {
      "date": "2026-04-29",
      "dailyHigh": "251.2",
      "dailyLow": "248.625",
      "dailyRange": "2.575",
      "fullAchievement": "3.65",
      "historicVol": "18.8%",
      "impliedVol": "",
      "weeklyHigh": "251.2",
      "weeklyLow": "241.65",
      "weeklyRange": "9.55",
      "sectionBreak": false,
      "dailyTarget": "2.95",
      "nextDailyTarget": "2.925",
      "dailyAchievement": "87.3%",
      "weeklyTarget": "6.975",
      "nextWeeklyTarget": "",
      "weeklyAchievement": "136.9%",
      "impliedVolTrend": "",
      "underTargetStreak": 1,
      "weeklyUnderTargetStreak": 0,
      "weeklyTrend": "up|3"
    },
    {
      "date": "2026-04-28",
      "dailyHigh": "249.375",
      "dailyLow": "245.075",
      "dailyRange": "4.3",
      "fullAchievement": "3.7",
      "historicVol": "19.0%",
      "impliedVol": "",
      "weeklyHigh": "249.375",
      "weeklyLow": "241.65",
      "weeklyRange": "7.725",
      "sectionBreak": false,
      "dailyTarget": "2.7",
      "nextDailyTarget": "2.95",
      "dailyAchievement": "159.3%",
      "weeklyTarget": "6.975",
      "nextWeeklyTarget": "",
      "weeklyAchievement": "110.8%",
      "impliedVolTrend": "",
      "underTargetStreak": 0,
      "weeklyUnderTargetStreak": 0,
      "weeklyTrend": "up|3"
    },
    {
      "date": "2026-04-27",
      "dailyHigh": "245.75",
      "dailyLow": "241.675",
      "dailyRange": "4.1",
      "fullAchievement": "3.375",
      "historicVol": "17.6%",
      "impliedVol": "",
      "weeklyHigh": "245.75",
      "weeklyLow": "241.65",
      "weeklyRange": "4.1",
      "sectionBreak": true,
      "dailyTarget": "2.225",
      "nextDailyTarget": "2.7",
      "dailyAchievement": "184.3%",
      "weeklyTarget": "6.975",
      "nextWeeklyTarget": "",
      "weeklyAchievement": "58.8%",
      "impliedVolTrend": "",
      "underTargetStreak": 0,
      "weeklyUnderTargetStreak": 0,
      "weeklyTrend": "up|3"
    },
    {
      "date": "2026-04-24",
      "dailyHigh": "242.85",
      "dailyLow": "240.325",
      "dailyRange": "2.7",
      "fullAchievement": "2.775",
      "historicVol": "14.7%",
      "impliedVol": "",
      "weeklyHigh": "244.5",
      "weeklyLow": "237",
      "weeklyRange": "7.5",
      "sectionBreak": false,
      "dailyTarget": "2.55",
      "nextDailyTarget": "2.225",
      "dailyAchievement": "105.9%",
      "weeklyTarget": "6.65",
      "nextWeeklyTarget": "6.975",
      "weeklyAchievement": "112.8%",
      "impliedVolTrend": "",
      "underTargetStreak": 0,
      "weeklyUnderTargetStreak": 0,
      "weeklyTrend": "up|2"
    },
    {
      "date": "2026-04-23",
      "dailyHigh": "240.325",
      "dailyLow": "237",
      "dailyRange": "3.325",
      "fullAchievement": "3.2",
      "historicVol": "17.1%",
      "impliedVol": "",
      "weeklyHigh": "244.5",
      "weeklyLow": "237",
      "weeklyRange": "7.5",
      "sectionBreak": false,
      "dailyTarget": "2.525",
      "nextDailyTarget": "2.55",
      "dailyAchievement": "131.7%",
      "weeklyTarget": "6.65",
      "nextWeeklyTarget": "",
      "weeklyAchievement": "112.8%",
      "impliedVolTrend": "",
      "underTargetStreak": 0,
      "weeklyUnderTargetStreak": 0,
      "weeklyTrend": "up|2"
    },
    {
      "date": "2026-04-22",
      "dailyHigh": "240.1",
      "dailyLow": "237.825",
      "dailyRange": "2.275",
      "fullAchievement": "3.15",
      "historicVol": "16.9%",
      "impliedVol": "",
      "weeklyHigh": "244.5",
      "weeklyLow": "237.825",
      "weeklyRange": "6.675",
      "sectionBreak": false,
      "dailyTarget": "3.325",
      "nextDailyTarget": "2.525",
      "dailyAchievement": "68.4%",
      "weeklyTarget": "6.65",
      "nextWeeklyTarget": "",
      "weeklyAchievement": "100.4%",
      "impliedVolTrend": "",
      "underTargetStreak": 1,
      "weeklyUnderTargetStreak": 0,
      "weeklyTrend": "up|2"
    },
    {
      "date": "2026-04-21",
      "dailyHigh": "242.7",
      "dailyLow": "238.7",
      "dailyRange": "4",
      "fullAchievement": "4.15",
      "historicVol": "22.2%",
      "impliedVol": "",
      "weeklyHigh": "244.5",
      "weeklyLow": "238.7",
      "weeklyRange": "5.8",
      "sectionBreak": false,
      "dailyTarget": "3.575",
      "nextDailyTarget": "3.325",
      "dailyAchievement": "111.9%",
      "weeklyTarget": "6.65",
      "nextWeeklyTarget": "",
      "weeklyAchievement": "87.2%",
      "impliedVolTrend": "",
      "underTargetStreak": 0,
      "weeklyUnderTargetStreak": 0,
      "weeklyTrend": "up|2"
    },
    {
      "date": "2026-04-20",
      "dailyHigh": "244.5",
      "dailyLow": "241.3",
      "dailyRange": "3.2",
      "fullAchievement": "4.475",
      "historicVol": "23.7%",
      "impliedVol": "",
      "weeklyHigh": "244.5",
      "weeklyLow": "241.3",
      "weeklyRange": "3.2",
      "sectionBreak": true,
      "dailyTarget": "3.35",
      "nextDailyTarget": "3.575",
      "dailyAchievement": "95.5%",
      "weeklyTarget": "6.65",
      "nextWeeklyTarget": "",
      "weeklyAchievement": "48.1%",
      "impliedVolTrend": "",
      "underTargetStreak": 1,
      "weeklyUnderTargetStreak": 0,
      "weeklyTrend": "up|2"
    },
    {
      "date": "2026-04-17",
      "dailyHigh": "244.05",
      "dailyLow": "238.775",
      "dailyRange": "5.275",
      "fullAchievement": "4.175",
      "historicVol": "22.0%",
      "impliedVol": "",
      "weeklyHigh": "247.675",
      "weeklyLow": "238.775",
      "weeklyRange": "8.9",
      "sectionBreak": false,
      "dailyTarget": "2.825",
      "nextDailyTarget": "3.35",
      "dailyAchievement": "186.7%",
      "weeklyTarget": "5.95",
      "nextWeeklyTarget": "6.65",
      "weeklyAchievement": "149.6%",
      "impliedVolTrend": "",
      "underTargetStreak": 0,
      "weeklyUnderTargetStreak": 0,
      "weeklyTrend": "up|1"
    },
    {
      "date": "2026-04-16",
      "dailyHigh": "246.975",
      "dailyLow": "242.05",
      "dailyRange": "4.925",
      "fullAchievement": "3.525",
      "historicVol": "18.6%",
      "impliedVol": "",
      "weeklyHigh": "247.675",
      "weeklyLow": "242.05",
      "weeklyRange": "5.625",
      "sectionBreak": false,
      "dailyTarget": "1.9",
      "nextDailyTarget": "2.825",
      "dailyAchievement": "259.2%",
      "weeklyTarget": "5.95",
      "nextWeeklyTarget": "",
      "weeklyAchievement": "94.5%",
      "impliedVolTrend": "",
      "underTargetStreak": 0,
      "weeklyUnderTargetStreak": 0,
      "weeklyTrend": "up|1"
    },
    {
      "date": "2026-04-15",
      "dailyHigh": "246.95",
      "dailyLow": "244.65",
      "dailyRange": "2.3",
      "fullAchievement": "2.375",
      "historicVol": "12.4%",
      "impliedVol": "",
      "weeklyHigh": "247.675",
      "weeklyLow": "243.95",
      "weeklyRange": "3.725",
      "sectionBreak": false,
      "dailyTarget": "1.9",
      "nextDailyTarget": "1.9",
      "dailyAchievement": "121.1%",
      "weeklyTarget": "5.95",
      "nextWeeklyTarget": "",
      "weeklyAchievement": "62.6%",
      "impliedVolTrend": "",
      "underTargetStreak": 0,
      "weeklyUnderTargetStreak": 0,
      "weeklyTrend": "up|1"
    },
    {
      "date": "2026-04-14",
      "dailyHigh": "247.675",
      "dailyLow": "244.3",
      "dailyRange": "3.375",
      "fullAchievement": "2.375",
      "historicVol": "12.4%",
      "impliedVol": "",
      "weeklyHigh": "247.675",
      "weeklyLow": "243.95",
      "weeklyRange": "3.725",
      "sectionBreak": false,
      "dailyTarget": "1.575",
      "nextDailyTarget": "1.9",
      "dailyAchievement": "214.3%",
      "weeklyTarget": "5.95",
      "nextWeeklyTarget": "",
      "weeklyAchievement": "62.6%",
      "impliedVolTrend": "",
      "underTargetStreak": 0,
      "weeklyUnderTargetStreak": 0,
      "weeklyTrend": "up|1"
    },
    {
      "date": "2026-04-13",
      "dailyHigh": "245.4",
      "dailyLow": "243.95",
      "dailyRange": "1.45",
      "fullAchievement": "1.975",
      "historicVol": "10.3%",
      "impliedVol": "",
      "weeklyHigh": "245.4",
      "weeklyLow": "243.95",
      "weeklyRange": "1.45",
      "sectionBreak": true,
      "dailyTarget": "1.9",
      "nextDailyTarget": "1.575",
      "dailyAchievement": "76.3%",
      "weeklyTarget": "5.95",
      "nextWeeklyTarget": "",
      "weeklyAchievement": "24.4%",
      "impliedVolTrend": "",
      "underTargetStreak": 1,
      "weeklyUnderTargetStreak": 0,
      "weeklyTrend": "up|1"
    },
    {
      "date": "2026-04-10",
      "dailyHigh": "245.675",
      "dailyLow": "243.45",
      "dailyRange": "2.325",
      "fullAchievement": "2.375",
      "historicVol": "12.4%",
      "impliedVol": "",
      "weeklyHigh": "245.675",
      "weeklyLow": "241.15",
      "weeklyRange": "4.525",
      "sectionBreak": false,
      "dailyTarget": "1.8",
      "nextDailyTarget": "1.9",
      "dailyAchievement": "129.2%",
      "weeklyTarget": "6.15",
      "nextWeeklyTarget": "5.95",
      "weeklyAchievement": "73.6%",
      "impliedVolTrend": "",
      "underTargetStreak": 0,
      "weeklyUnderTargetStreak": 0,
      "weeklyTrend": "down|1"
    },
    {
      "date": "2026-04-09",
      "dailyHigh": "243.625",
      "dailyLow": "241.5",
      "dailyRange": "2.125",
      "fullAchievement": "2.25",
      "historicVol": "11.9%",
      "impliedVol": "",
      "weeklyHigh": "244",
      "weeklyLow": "241.15",
      "weeklyRange": "2.85",
      "sectionBreak": false,
      "dailyTarget": "1.75",
      "nextDailyTarget": "1.8",
      "dailyAchievement": "121.4%",
      "weeklyTarget": "6.15",
      "nextWeeklyTarget": "",
      "weeklyAchievement": "46.3%",
      "impliedVolTrend": "",
      "underTargetStreak": 0,
      "weeklyUnderTargetStreak": 0,
      "weeklyTrend": "down|1"
    },
    {
      "date": "2026-04-08",
      "dailyHigh": "244",
      "dailyLow": "241.35",
      "dailyRange": "2.65",
      "fullAchievement": "2.2",
      "historicVol": "11.6%",
      "impliedVol": "",
      "weeklyHigh": "244",
      "weeklyLow": "241.15",
      "weeklyRange": "2.85",
      "sectionBreak": false,
      "dailyTarget": "2.2",
      "nextDailyTarget": "1.75",
      "dailyAchievement": "120.5%",
      "weeklyTarget": "6.15",
      "nextWeeklyTarget": "",
      "weeklyAchievement": "46.3%",
      "impliedVolTrend": "",
      "underTargetStreak": 0,
      "weeklyUnderTargetStreak": 0,
      "weeklyTrend": "down|1"
    },
    {
      "date": "2026-04-07",
      "dailyHigh": "243.15",
      "dailyLow": "241.15",
      "dailyRange": "2",
      "fullAchievement": "2.75",
      "historicVol": "14.5%",
      "impliedVol": "",
      "weeklyHigh": "243.75",
      "weeklyLow": "241.15",
      "weeklyRange": "2.6",
      "sectionBreak": false,
      "dailyTarget": "2.15",
      "nextDailyTarget": "2.2",
      "dailyAchievement": "93.0%",
      "weeklyTarget": "6.15",
      "nextWeeklyTarget": "",
      "weeklyAchievement": "42.3%",
      "impliedVolTrend": "",
      "underTargetStreak": 2,
      "weeklyUnderTargetStreak": 0,
      "weeklyTrend": "down|1"
    },
    {
      "date": "2026-04-06",
      "dailyHigh": "243.75",
      "dailyLow": "241.825",
      "dailyRange": "1.925",
      "fullAchievement": "2.675",
      "historicVol": "14.1%",
      "impliedVol": "",
      "weeklyHigh": "243.75",
      "weeklyLow": "241.825",
      "weeklyRange": "1.925",
      "sectionBreak": true,
      "dailyTarget": "2.425",
      "nextDailyTarget": "2.15",
      "dailyAchievement": "79.4%",
      "weeklyTarget": "6.15",
      "nextWeeklyTarget": "",
      "weeklyAchievement": "31.3%",
      "impliedVolTrend": "",
      "underTargetStreak": 1,
      "weeklyUnderTargetStreak": 0,
      "weeklyTrend": "down|1"
    },
    {
      "date": "2026-04-02",
      "dailyHigh": "242.6",
      "dailyLow": "238.275",
      "dailyRange": "4.325",
      "fullAchievement": "3.025",
      "historicVol": "15.9%",
      "impliedVol": "",
      "weeklyHigh": "242.6",
      "weeklyLow": "236.05",
      "weeklyRange": "6.55",
      "sectionBreak": false,
      "dailyTarget": "1.9",
      "nextDailyTarget": "2.425",
      "dailyAchievement": "227.6%",
      "weeklyTarget": "6.3",
      "nextWeeklyTarget": "6.15",
      "weeklyAchievement": "104.0%",
      "impliedVolTrend": "",
      "underTargetStreak": 0,
      "weeklyUnderTargetStreak": 0,
      "weeklyTrend": "up|1"
    },
    {
      "date": "2026-04-01",
      "dailyHigh": "241.25",
      "dailyLow": "239.5",
      "dailyRange": "1.75",
      "fullAchievement": "2.375",
      "historicVol": "12.6%",
      "impliedVol": "",
      "weeklyHigh": "241.25",
      "weeklyLow": "236.05",
      "weeklyRange": "5.2",
      "sectionBreak": false,
      "dailyTarget": "2.625",
      "nextDailyTarget": "1.9",
      "dailyAchievement": "66.7%",
      "weeklyTarget": "6.3",
      "nextWeeklyTarget": "",
      "weeklyAchievement": "82.5%",
      "impliedVolTrend": "",
      "underTargetStreak": 1,
      "weeklyUnderTargetStreak": 0,
      "weeklyTrend": "up|1"
    },
    {
      "date": "2026-03-31",
      "dailyHigh": "239.875",
      "dailyLow": "236.9",
      "dailyRange": "2.975",
      "fullAchievement": "3.275",
      "historicVol": "17.5%",
      "impliedVol": "",
      "weeklyHigh": "239.875",
      "weeklyLow": "236.05",
      "weeklyRange": "3.825",
      "sectionBreak": false,
      "dailyTarget": "2.5",
      "nextDailyTarget": "2.625",
      "dailyAchievement": "119.0%",
      "weeklyTarget": "6.3",
      "nextWeeklyTarget": "",
      "weeklyAchievement": "60.7%",
      "impliedVolTrend": "",
      "underTargetStreak": 0,
      "weeklyUnderTargetStreak": 0,
      "weeklyTrend": "up|1"
    },
    {
      "date": "2026-03-30",
      "dailyHigh": "238.425",
      "dailyLow": "236.05",
      "dailyRange": "2.375",
      "fullAchievement": "3.125",
      "historicVol": "16.9%",
      "impliedVol": "",
      "weeklyHigh": "238.425",
      "weeklyLow": "236.05",
      "weeklyRange": "2.375",
      "sectionBreak": true,
      "dailyTarget": "2.75",
      "nextDailyTarget": "2.5",
      "dailyAchievement": "86.4%",
      "weeklyTarget": "6.3",
      "nextWeeklyTarget": "",
      "weeklyAchievement": "37.7%",
      "impliedVolTrend": "",
      "underTargetStreak": 1,
      "weeklyUnderTargetStreak": 0,
      "weeklyTrend": "up|1"
    },
    {
      "date": "2026-03-27",
      "dailyHigh": "236.775",
      "dailyLow": "232.3",
      "dailyRange": "4.475",
      "fullAchievement": "3.425",
      "historicVol": "18.6%",
      "impliedVol": "",
      "weeklyHigh": "236.775",
      "weeklyLow": "229.975",
      "weeklyRange": "6.8",
      "sectionBreak": false,
      "dailyTarget": "2.15",
      "nextDailyTarget": "2.75",
      "dailyAchievement": "208.1%",
      "weeklyTarget": "7.375",
      "nextWeeklyTarget": "6.3",
      "weeklyAchievement": "92.2%",
      "impliedVolTrend": "",
      "underTargetStreak": 0,
      "weeklyUnderTargetStreak": 0,
      "weeklyTrend": "down|3"
    },
    {
      "date": "2026-03-26",
      "dailyHigh": "232.8",
      "dailyLow": "230.275",
      "dailyRange": "2.525",
      "fullAchievement": "2.7",
      "historicVol": "14.9%",
      "impliedVol": "",
      "weeklyHigh": "233.4",
      "weeklyLow": "229.975",
      "weeklyRange": "3.425",
      "sectionBreak": false,
      "dailyTarget": "2.05",
      "nextDailyTarget": "2.15",
      "dailyAchievement": "123.2%",
      "weeklyTarget": "7.375",
      "nextWeeklyTarget": "",
      "weeklyAchievement": "46.4%",
      "impliedVolTrend": "",
      "underTargetStreak": 0,
      "weeklyUnderTargetStreak": 0,
      "weeklyTrend": "down|3"
    },
    {
      "date": "2026-03-25",
      "dailyHigh": "233.4",
      "dailyLow": "230.125",
      "dailyRange": "3.275",
      "fullAchievement": "2.575",
      "historicVol": "14.2%",
      "impliedVol": "",
      "weeklyHigh": "233.4",
      "weeklyLow": "229.975",
      "weeklyRange": "3.425",
      "sectionBreak": false,
      "dailyTarget": "1.975",
      "nextDailyTarget": "2.05",
      "dailyAchievement": "165.8%",
      "weeklyTarget": "7.375",
      "nextWeeklyTarget": "",
      "weeklyAchievement": "46.4%",
      "impliedVolTrend": "",
      "underTargetStreak": 0,
      "weeklyUnderTargetStreak": 0,
      "weeklyTrend": "down|3"
    },
    {
      "date": "2026-03-24",
      "dailyHigh": "233",
      "dailyLow": "230.7",
      "dailyRange": "2.3",
      "fullAchievement": "2.475",
      "historicVol": "13.6%",
      "impliedVol": "",
      "weeklyHigh": "233",
      "weeklyLow": "229.975",
      "weeklyRange": "3.025",
      "sectionBreak": false,
      "dailyTarget": "2.175",
      "nextDailyTarget": "1.975",
      "dailyAchievement": "105.7%",
      "weeklyTarget": "7.375",
      "nextWeeklyTarget": "",
      "weeklyAchievement": "41.0%",
      "impliedVolTrend": "",
      "underTargetStreak": 0,
      "weeklyUnderTargetStreak": 0,
      "weeklyTrend": "down|3"
    },
    {
      "date": "2026-03-23",
      "dailyHigh": "232.1",
      "dailyLow": "229.975",
      "dailyRange": "2.125",
      "fullAchievement": "2.725",
      "historicVol": "15.1%",
      "impliedVol": "",
      "weeklyHigh": "232.1",
      "weeklyLow": "229.975",
      "weeklyRange": "2.125",
      "sectionBreak": true,
      "dailyTarget": "2.1",
      "nextDailyTarget": "2.175",
      "dailyAchievement": "101.2%",
      "weeklyTarget": "7.375",
      "nextWeeklyTarget": "",
      "weeklyAchievement": "28.8%",
      "impliedVolTrend": "",
      "underTargetStreak": 0,
      "weeklyUnderTargetStreak": 0,
      "weeklyTrend": "down|3"
    },
    {
      "date": "2026-03-20",
      "dailyHigh": "231.775",
      "dailyLow": "228.775",
      "dailyRange": "3",
      "fullAchievement": "2.625",
      "historicVol": "14.6%",
      "impliedVol": "",
      "weeklyHigh": "231.925",
      "weeklyLow": "226.825",
      "weeklyRange": "5.1",
      "sectionBreak": false,
      "dailyTarget": "1.85",
      "nextDailyTarget": "2.1",
      "dailyAchievement": "162.2%",
      "weeklyTarget": "8.5",
      "nextWeeklyTarget": "7.375",
      "weeklyAchievement": "60.0%",
      "impliedVolTrend": "",
      "underTargetStreak": 0,
      "weeklyUnderTargetStreak": 0,
      "weeklyTrend": "down|2"
    },
    {
      "date": "2026-03-19",
      "dailyHigh": "231.05",
      "dailyLow": "228.525",
      "dailyRange": "3.075",
      "fullAchievement": "2.325",
      "historicVol": "12.9%",
      "impliedVol": "",
      "weeklyHigh": "231.925",
      "weeklyLow": "226.825",
      "weeklyRange": "5.1",
      "sectionBreak": false,
      "dailyTarget": "1.9",
      "nextDailyTarget": "1.85",
      "dailyAchievement": "161.8%",
      "weeklyTarget": "8.5",
      "nextWeeklyTarget": "",
      "weeklyAchievement": "60.0%",
      "impliedVolTrend": "",
      "underTargetStreak": 0,
      "weeklyUnderTargetStreak": 0,
      "weeklyTrend": "down|2"
    },
    {
      "date": "2026-03-18",
      "dailyHigh": "231.925",
      "dailyLow": "230.125",
      "dailyRange": "1.8",
      "fullAchievement": "2.375",
      "historicVol": "13.1%",
      "impliedVol": "",
      "weeklyHigh": "231.925",
      "weeklyLow": "226.825",
      "weeklyRange": "5.1",
      "sectionBreak": false,
      "dailyTarget": "2.225",
      "nextDailyTarget": "1.9",
      "dailyAchievement": "80.9%",
      "weeklyTarget": "8.5",
      "nextWeeklyTarget": "",
      "weeklyAchievement": "60.0%",
      "impliedVolTrend": "",
      "underTargetStreak": 2,
      "weeklyUnderTargetStreak": 0,
      "weeklyTrend": "down|2"
    },
    {
      "date": "2026-03-17",
      "dailyHigh": "231.75",
      "dailyLow": "229.675",
      "dailyRange": "2.075",
      "fullAchievement": "2.775",
      "historicVol": "15.3%",
      "impliedVol": "",
      "weeklyHigh": "231.75",
      "weeklyLow": "226.825",
      "weeklyRange": "4.925",
      "sectionBreak": false,
      "dailyTarget": "2.55",
      "nextDailyTarget": "2.225",
      "dailyAchievement": "81.4%",
      "weeklyTarget": "8.5",
      "nextWeeklyTarget": "",
      "weeklyAchievement": "57.9%",
      "impliedVolTrend": "",
      "underTargetStreak": 1,
      "weeklyUnderTargetStreak": 0,
      "weeklyTrend": "down|2"
    },
    {
      "date": "2026-03-16",
      "dailyHigh": "230.075",
      "dailyLow": "226.825",
      "dailyRange": "3.25",
      "fullAchievement": "3.175",
      "historicVol": "17.6%",
      "impliedVol": "",
      "weeklyHigh": "230.075",
      "weeklyLow": "226.825",
      "weeklyRange": "3.25",
      "sectionBreak": true,
      "dailyTarget": "2.4",
      "nextDailyTarget": "2.55",
      "dailyAchievement": "135.4%",
      "weeklyTarget": "8.5",
      "nextWeeklyTarget": "",
      "weeklyAchievement": "38.2%",
      "impliedVolTrend": "",
      "underTargetStreak": 0,
      "weeklyUnderTargetStreak": 0,
      "weeklyTrend": "down|2"
    },
    {
      "date": "2026-03-13",
      "dailyHigh": "228.95",
      "dailyLow": "225.975",
      "dailyRange": "2.975",
      "fullAchievement": "3",
      "historicVol": "16.9%",
      "impliedVol": "",
      "weeklyHigh": "229.25",
      "weeklyLow": "222.275",
      "weeklyRange": "6.975",
      "sectionBreak": false,
      "dailyTarget": "2.45",
      "nextDailyTarget": "2.4",
      "dailyAchievement": "121.4%",
      "weeklyTarget": "7.225",
      "nextWeeklyTarget": "8.5",
      "weeklyAchievement": "96.5%",
      "impliedVolTrend": "",
      "underTargetStreak": 0,
      "weeklyUnderTargetStreak": 0,
      "weeklyTrend": "down|1"
    },
    {
      "date": "2026-03-12",
      "dailyHigh": "228.125",
      "dailyLow": "224.85",
      "dailyRange": "3.275",
      "fullAchievement": "3.05",
      "historicVol": "17.2%",
      "impliedVol": "",
      "weeklyHigh": "229.25",
      "weeklyLow": "222.275",
      "weeklyRange": "6.975",
      "sectionBreak": false,
      "dailyTarget": "3.45",
      "nextDailyTarget": "2.45",
      "dailyAchievement": "94.9%",
      "weeklyTarget": "7.225",
      "nextWeeklyTarget": "",
      "weeklyAchievement": "96.5%",
      "impliedVolTrend": "",
      "underTargetStreak": 3,
      "weeklyUnderTargetStreak": 0,
      "weeklyTrend": "down|1"
    },
    {
      "date": "2026-03-11",
      "dailyHigh": "227.625",
      "dailyLow": "225.6",
      "dailyRange": "2.75",
      "fullAchievement": "4.3",
      "historicVol": "24.3%",
      "impliedVol": "",
      "weeklyHigh": "229.25",
      "weeklyLow": "222.275",
      "weeklyRange": "6.975",
      "sectionBreak": false,
      "dailyTarget": "4.125",
      "nextDailyTarget": "3.45",
      "dailyAchievement": "66.7%",
      "weeklyTarget": "7.225",
      "nextWeeklyTarget": "",
      "weeklyAchievement": "96.5%",
      "impliedVolTrend": "",
      "underTargetStreak": 2,
      "weeklyUnderTargetStreak": 0,
      "weeklyTrend": "down|1"
    },
    {
      "date": "2026-03-10",
      "dailyHigh": "228.725",
      "dailyLow": "226.45",
      "dailyRange": "3.15",
      "fullAchievement": "5.15",
      "historicVol": "28.9%",
      "impliedVol": "",
      "weeklyHigh": "229.25",
      "weeklyLow": "222.275",
      "weeklyRange": "6.975",
      "sectionBreak": false,
      "dailyTarget": "3.825",
      "nextDailyTarget": "4.125",
      "dailyAchievement": "82.4%",
      "weeklyTarget": "7.225",
      "nextWeeklyTarget": "",
      "weeklyAchievement": "96.5%",
      "impliedVolTrend": "",
      "underTargetStreak": 1,
      "weeklyUnderTargetStreak": 0,
      "weeklyTrend": "down|1"
    },
    {
      "date": "2026-03-09",
      "dailyHigh": "226.25",
      "dailyLow": "222.275",
      "dailyRange": "6.975",
      "fullAchievement": "4.775",
      "historicVol": "27.1%",
      "impliedVol": "",
      "weeklyHigh": "229.25",
      "weeklyLow": "222.275",
      "weeklyRange": "6.975",
      "sectionBreak": true,
      "dailyTarget": "3.35",
      "nextDailyTarget": "3.825",
      "dailyAchievement": "208.2%",
      "weeklyTarget": "7.225",
      "nextWeeklyTarget": "",
      "weeklyAchievement": "96.5%",
      "impliedVolTrend": "",
      "underTargetStreak": 0,
      "weeklyUnderTargetStreak": 0,
      "weeklyTrend": "down|1"
    },
    {
      "date": "2026-03-06",
      "dailyHigh": "233.575",
      "dailyLow": "228.225",
      "dailyRange": "5.35",
      "fullAchievement": "4.175",
      "historicVol": "23.3%",
      "impliedVol": "",
      "weeklyHigh": "234.325",
      "weeklyLow": "224.25",
      "weeklyRange": "10.075",
      "sectionBreak": false,
      "dailyTarget": "2.85",
      "nextDailyTarget": "3.35",
      "dailyAchievement": "187.7%",
      "weeklyTarget": "5",
      "nextWeeklyTarget": "7.225",
      "weeklyAchievement": "201.5%",
      "impliedVolTrend": "",
      "underTargetStreak": 0,
      "weeklyUnderTargetStreak": 0,
      "weeklyTrend": "up|2"
    },
    {
      "date": "2026-03-05",
      "dailyHigh": "234.325",
      "dailyLow": "232.325",
      "dailyRange": "2",
      "fullAchievement": "3.575",
      "historicVol": "19.7%",
      "impliedVol": "",
      "weeklyHigh": "234.325",
      "weeklyLow": "224.25",
      "weeklyRange": "10.075",
      "sectionBreak": false,
      "dailyTarget": "3.55",
      "nextDailyTarget": "2.85",
      "dailyAchievement": "56.3%",
      "weeklyTarget": "5",
      "nextWeeklyTarget": "",
      "weeklyAchievement": "201.5%",
      "impliedVolTrend": "",
      "underTargetStreak": 1,
      "weeklyUnderTargetStreak": 0,
      "weeklyTrend": "up|2"
    },
    {
      "date": "2026-03-04",
      "dailyHigh": "234.075",
      "dailyLow": "229.4",
      "dailyRange": "5.175",
      "fullAchievement": "4.45",
      "historicVol": "24.5%",
      "impliedVol": "",
      "weeklyHigh": "234.075",
      "weeklyLow": "224.25",
      "weeklyRange": "9.825",
      "sectionBreak": false,
      "dailyTarget": "3.35",
      "nextDailyTarget": "3.55",
      "dailyAchievement": "154.5%",
      "weeklyTarget": "5",
      "nextWeeklyTarget": "",
      "weeklyAchievement": "196.5%",
      "impliedVolTrend": "",
      "underTargetStreak": 0,
      "weeklyUnderTargetStreak": 0,
      "weeklyTrend": "up|2"
    },
    {
      "date": "2026-03-03",
      "dailyHigh": "229.075",
      "dailyLow": "225.5",
      "dailyRange": "3.575",
      "fullAchievement": "4.2",
      "historicVol": "23.5%",
      "impliedVol": "",
      "weeklyHigh": "229.075",
      "weeklyLow": "224.25",
      "weeklyRange": "4.825",
      "sectionBreak": false,
      "dailyTarget": "3.6",
      "nextDailyTarget": "3.35",
      "dailyAchievement": "99.3%",
      "weeklyTarget": "5",
      "nextWeeklyTarget": "",
      "weeklyAchievement": "96.5%",
      "impliedVolTrend": "",
      "underTargetStreak": 1,
      "weeklyUnderTargetStreak": 0,
      "weeklyTrend": "up|2"
    },
    {
      "date": "2026-03-02",
      "dailyHigh": "228.875",
      "dailyLow": "224.25",
      "dailyRange": "4.625",
      "fullAchievement": "4.5",
      "historicVol": "25.2%",
      "impliedVol": "",
      "weeklyHigh": "228.875",
      "weeklyLow": "224.25",
      "weeklyRange": "4.625",
      "sectionBreak": true,
      "dailyTarget": "3",
      "nextDailyTarget": "3.6",
      "dailyAchievement": "154.2%",
      "weeklyTarget": "5",
      "nextWeeklyTarget": "",
      "weeklyAchievement": "92.5%",
      "impliedVolTrend": "",
      "underTargetStreak": 0,
      "weeklyUnderTargetStreak": 0,
      "weeklyTrend": "up|2"
    },
    {
      "date": "2026-02-27",
      "dailyHigh": "231.85",
      "dailyLow": "227.45",
      "dailyRange": "4.4",
      "fullAchievement": "3.75",
      "historicVol": "21.0%",
      "impliedVol": "",
      "weeklyHigh": "235.9",
      "weeklyLow": "227.45",
      "weeklyRange": "8.45",
      "sectionBreak": false,
      "dailyTarget": "2.325",
      "nextDailyTarget": "3",
      "dailyAchievement": "189.2%",
      "weeklyTarget": "5.175",
      "nextWeeklyTarget": "5",
      "weeklyAchievement": "163.3%",
      "impliedVolTrend": "",
      "underTargetStreak": 0,
      "weeklyUnderTargetStreak": 0,
      "weeklyTrend": "up|1"
    },
    {
      "date": "2026-02-26",
      "dailyHigh": "234.5",
      "dailyLow": "230.15",
      "dailyRange": "4.45",
      "fullAchievement": "2.9",
      "historicVol": "16.0%",
      "impliedVol": "",
      "weeklyHigh": "235.9",
      "weeklyLow": "230.15",
      "weeklyRange": "5.75",
      "sectionBreak": false,
      "dailyTarget": "2.2",
      "nextDailyTarget": "2.325",
      "dailyAchievement": "202.3%",
      "weeklyTarget": "5.175",
      "nextWeeklyTarget": "",
      "weeklyAchievement": "111.1%",
      "impliedVolTrend": "",
      "underTargetStreak": 0,
      "weeklyUnderTargetStreak": 0,
      "weeklyTrend": "up|1"
    },
    {
      "date": "2026-02-25",
      "dailyHigh": "235.85",
      "dailyLow": "233.475",
      "dailyRange": "2.375",
      "fullAchievement": "2.75",
      "historicVol": "15.0%",
      "impliedVol": "",
      "weeklyHigh": "235.9",
      "weeklyLow": "231.925",
      "weeklyRange": "3.975",
      "sectionBreak": false,
      "dailyTarget": "2.25",
      "nextDailyTarget": "2.2",
      "dailyAchievement": "105.6%",
      "weeklyTarget": "5.175",
      "nextWeeklyTarget": "",
      "weeklyAchievement": "76.8%",
      "impliedVolTrend": "",
      "underTargetStreak": 0,
      "weeklyUnderTargetStreak": 0,
      "weeklyTrend": "up|1"
    },
    {
      "date": "2026-02-24",
      "dailyHigh": "233.875",
      "dailyLow": "232",
      "dailyRange": "1.875",
      "fullAchievement": "2.8",
      "historicVol": "15.3%",
      "impliedVol": "",
      "weeklyHigh": "235.9",
      "weeklyLow": "231.925",
      "weeklyRange": "3.975",
      "sectionBreak": false,
      "dailyTarget": "2.2",
      "nextDailyTarget": "2.25",
      "dailyAchievement": "85.2%",
      "weeklyTarget": "5.175",
      "nextWeeklyTarget": "",
      "weeklyAchievement": "76.8%",
      "impliedVolTrend": "",
      "underTargetStreak": 1,
      "weeklyUnderTargetStreak": 0,
      "weeklyTrend": "up|1"
    },
    {
      "date": "2026-02-23",
      "dailyHigh": "235.9",
      "dailyLow": "231.925",
      "dailyRange": "3.975",
      "fullAchievement": "2.75",
      "historicVol": "15.1%",
      "impliedVol": "",
      "weeklyHigh": "235.9",
      "weeklyLow": "231.925",
      "weeklyRange": "3.975",
      "sectionBreak": true,
      "dailyTarget": "1.4",
      "nextDailyTarget": "2.2",
      "dailyAchievement": "283.9%",
      "weeklyTarget": "5.175",
      "nextWeeklyTarget": "",
      "weeklyAchievement": "76.8%",
      "impliedVolTrend": "",
      "underTargetStreak": 0,
      "weeklyUnderTargetStreak": 0,
      "weeklyTrend": "up|1"
    },
    {
      "date": "2026-02-20",
      "dailyHigh": "236.45",
      "dailyLow": "233.925",
      "dailyRange": "2.525",
      "fullAchievement": "1.75",
      "historicVol": "9.6%",
      "impliedVol": "",
      "weeklyHigh": "236.875",
      "weeklyLow": "233.725",
      "weeklyRange": "3.15",
      "sectionBreak": false,
      "dailyTarget": "1.45",
      "nextDailyTarget": "1.4",
      "dailyAchievement": "174.1%",
      "weeklyTarget": "5.675",
      "nextWeeklyTarget": "5.175",
      "weeklyAchievement": "55.5%",
      "impliedVolTrend": "",
      "underTargetStreak": 0,
      "weeklyUnderTargetStreak": 0,
      "weeklyTrend": "down|2"
    },
    {
      "date": "2026-02-19",
      "dailyHigh": "236.875",
      "dailyLow": "235.125",
      "dailyRange": "1.75",
      "fullAchievement": "1.825",
      "historicVol": "9.8%",
      "impliedVol": "",
      "weeklyHigh": "236.875",
      "weeklyLow": "233.725",
      "weeklyRange": "3.15",
      "sectionBreak": false,
      "dailyTarget": "1.525",
      "nextDailyTarget": "1.45",
      "dailyAchievement": "114.8%",
      "weeklyTarget": "5.675",
      "nextWeeklyTarget": "",
      "weeklyAchievement": "55.5%",
      "impliedVolTrend": "",
      "underTargetStreak": 0,
      "weeklyUnderTargetStreak": 0,
      "weeklyTrend": "down|2"
    },
    {
      "date": "2026-02-18",
      "dailyHigh": "236.35",
      "dailyLow": "235.35",
      "dailyRange": "1",
      "fullAchievement": "1.9",
      "historicVol": "10.3%",
      "impliedVol": "",
      "weeklyHigh": "236.425",
      "weeklyLow": "233.725",
      "weeklyRange": "2.7",
      "sectionBreak": false,
      "dailyTarget": "1.8",
      "nextDailyTarget": "1.525",
      "dailyAchievement": "55.6%",
      "weeklyTarget": "5.675",
      "nextWeeklyTarget": "",
      "weeklyAchievement": "47.6%",
      "impliedVolTrend": "",
      "underTargetStreak": 1,
      "weeklyUnderTargetStreak": 0,
      "weeklyTrend": "down|2"
    },
    {
      "date": "2026-02-17",
      "dailyHigh": "236.425",
      "dailyLow": "235.025",
      "dailyRange": "2.7",
      "fullAchievement": "2.25",
      "historicVol": "12.3%",
      "impliedVol": "",
      "weeklyHigh": "236.425",
      "weeklyLow": "233.725",
      "weeklyRange": "2.7",
      "sectionBreak": true,
      "dailyTarget": "1.825",
      "nextDailyTarget": "1.8",
      "dailyAchievement": "147.9%",
      "weeklyTarget": "5.675",
      "nextWeeklyTarget": "",
      "weeklyAchievement": "47.6%",
      "impliedVolTrend": "",
      "underTargetStreak": 0,
      "weeklyUnderTargetStreak": 0,
      "weeklyTrend": "down|2"
    },
    {
      "date": "2026-02-13",
      "dailyHigh": "234.875",
      "dailyLow": "232.875",
      "dailyRange": "2",
      "fullAchievement": "2.275",
      "historicVol": "12.4%",
      "impliedVol": "",
      "weeklyHigh": "234.875",
      "weeklyLow": "231.475",
      "weeklyRange": "3.4",
      "sectionBreak": false,
      "dailyTarget": "1.775",
      "nextDailyTarget": "1.825",
      "dailyAchievement": "112.7%",
      "weeklyTarget": "6.05",
      "nextWeeklyTarget": "5.675",
      "weeklyAchievement": "56.2%",
      "impliedVolTrend": "",
      "underTargetStreak": 0,
      "weeklyUnderTargetStreak": 0,
      "weeklyTrend": "down|1"
    },
    {
      "date": "2026-02-12",
      "dailyHigh": "234.575",
      "dailyLow": "232.5",
      "dailyRange": "2.075",
      "fullAchievement": "2.225",
      "historicVol": "12.1%",
      "impliedVol": "",
      "weeklyHigh": "234.575",
      "weeklyLow": "231.475",
      "weeklyRange": "3.1",
      "sectionBreak": false,
      "dailyTarget": "1.9",
      "nextDailyTarget": "1.775",
      "dailyAchievement": "109.2%",
      "weeklyTarget": "6.05",
      "nextWeeklyTarget": "",
      "weeklyAchievement": "51.2%",
      "impliedVolTrend": "",
      "underTargetStreak": 0,
      "weeklyUnderTargetStreak": 0,
      "weeklyTrend": "down|1"
    },
    {
      "date": "2026-02-11",
      "dailyHigh": "234.5",
      "dailyLow": "231.775",
      "dailyRange": "2.725",
      "fullAchievement": "2.375",
      "historicVol": "12.9%",
      "impliedVol": "",
      "weeklyHigh": "234.5",
      "weeklyLow": "231.475",
      "weeklyRange": "3.025",
      "sectionBreak": false,
      "dailyTarget": "2.375",
      "nextDailyTarget": "1.9",
      "dailyAchievement": "114.7%",
      "weeklyTarget": "6.05",
      "nextWeeklyTarget": "",
      "weeklyAchievement": "50.0%",
      "impliedVolTrend": "",
      "underTargetStreak": 0,
      "weeklyUnderTargetStreak": 0,
      "weeklyTrend": "down|1"
    },
    {
      "date": "2026-02-10",
      "dailyHigh": "233.5",
      "dailyLow": "231.65",
      "dailyRange": "1.85",
      "fullAchievement": "2.975",
      "historicVol": "16.4%",
      "impliedVol": "",
      "weeklyHigh": "234",
      "weeklyLow": "231.475",
      "weeklyRange": "2.525",
      "sectionBreak": false,
      "dailyTarget": "3.825",
      "nextDailyTarget": "2.375",
      "dailyAchievement": "48.4%",
      "weeklyTarget": "6.05",
      "nextWeeklyTarget": "",
      "weeklyAchievement": "41.7%",
      "impliedVolTrend": "",
      "underTargetStreak": 2,
      "weeklyUnderTargetStreak": 0,
      "weeklyTrend": "down|1"
    },
    {
      "date": "2026-02-09",
      "dailyHigh": "234",
      "dailyLow": "231.475",
      "dailyRange": "2.525",
      "fullAchievement": "4.775",
      "historicVol": "26.3%",
      "impliedVol": "",
      "weeklyHigh": "234",
      "weeklyLow": "231.475",
      "weeklyRange": "2.525",
      "sectionBreak": true,
      "dailyTarget": "3.875",
      "nextDailyTarget": "3.825",
      "dailyAchievement": "65.2%",
      "weeklyTarget": "6.05",
      "nextWeeklyTarget": "",
      "weeklyAchievement": "41.7%",
      "impliedVolTrend": "",
      "underTargetStreak": 1,
      "weeklyUnderTargetStreak": 0,
      "weeklyTrend": "down|1"
    },
    {
      "date": "2026-02-06",
      "dailyHigh": "235",
      "dailyLow": "231.2",
      "dailyRange": "4.55",
      "fullAchievement": "4.85",
      "historicVol": "26.7%",
      "impliedVol": "",
      "weeklyHigh": "236.45",
      "weeklyLow": "227.475",
      "weeklyRange": "8.975",
      "sectionBreak": false,
      "dailyTarget": "3.45",
      "nextDailyTarget": "3.875",
      "dailyAchievement": "131.9%",
      "weeklyTarget": "",
      "nextWeeklyTarget": "6.05",
      "weeklyAchievement": "",
      "impliedVolTrend": "",
      "underTargetStreak": 0,
      "weeklyUnderTargetStreak": 0,
      "weeklyTrend": ""
    },
    {
      "date": "2026-02-05",
      "dailyHigh": "233.5",
      "dailyLow": "227.475",
      "dailyRange": "7.25",
      "fullAchievement": "4.3",
      "historicVol": "23.9%",
      "impliedVol": "",
      "weeklyHigh": "236.45",
      "weeklyLow": "227.475",
      "weeklyRange": "8.975",
      "sectionBreak": false,
      "dailyTarget": "2.45",
      "nextDailyTarget": "3.45",
      "dailyAchievement": "295.9%",
      "weeklyTarget": "",
      "nextWeeklyTarget": "",
      "weeklyAchievement": "",
      "impliedVolTrend": "",
      "underTargetStreak": 0,
      "weeklyUnderTargetStreak": 0,
      "weeklyTrend": ""
    },
    {
      "date": "2026-02-04",
      "dailyHigh": "236.45",
      "dailyLow": "233.7",
      "dailyRange": "2.75",
      "fullAchievement": "3.05",
      "historicVol": "16.7%",
      "impliedVol": "",
      "weeklyHigh": "236.45",
      "weeklyLow": "228.975",
      "weeklyRange": "7.475",
      "sectionBreak": false,
      "dailyTarget": "2.75",
      "nextDailyTarget": "2.45",
      "dailyAchievement": "100.0%",
      "weeklyTarget": "",
      "nextWeeklyTarget": "",
      "weeklyAchievement": "",
      "impliedVolTrend": "",
      "underTargetStreak": 0,
      "weeklyUnderTargetStreak": 0,
      "weeklyTrend": ""
    },
    {
      "date": "2026-02-03",
      "dailyHigh": "233.975",
      "dailyLow": "231.075",
      "dailyRange": "2.9",
      "fullAchievement": "3.425",
      "historicVol": "18.7%",
      "impliedVol": "",
      "weeklyHigh": "233.975",
      "weeklyLow": "228.975",
      "weeklyRange": "5",
      "sectionBreak": false,
      "dailyTarget": "2.525",
      "nextDailyTarget": "2.75",
      "dailyAchievement": "114.9%",
      "weeklyTarget": "",
      "nextWeeklyTarget": "",
      "weeklyAchievement": "",
      "impliedVolTrend": "",
      "underTargetStreak": 0,
      "weeklyUnderTargetStreak": 0,
      "weeklyTrend": ""
    },
    {
      "date": "2026-02-02",
      "dailyHigh": "232.5",
      "dailyLow": "230",
      "dailyRange": "3.525",
      "fullAchievement": "3.15",
      "historicVol": "17.5%",
      "impliedVol": "",
      "weeklyHigh": "232.5",
      "weeklyLow": "228.975",
      "weeklyRange": "3.525",
      "sectionBreak": true,
      "dailyTarget": "2.375",
      "nextDailyTarget": "2.525",
      "dailyAchievement": "148.4%",
      "weeklyTarget": "",
      "nextWeeklyTarget": "",
      "weeklyAchievement": "",
      "impliedVolTrend": "",
      "underTargetStreak": 0,
      "weeklyUnderTargetStreak": 0,
      "weeklyTrend": ""
    },
    {
      "date": "2026-01-30",
      "dailyHigh": "232.3",
      "dailyLow": "228.475",
      "dailyRange": "3.825",
      "fullAchievement": "2.975",
      "historicVol": "16.7%",
      "impliedVol": "",
      "weeklyHigh": "233.15",
      "weeklyLow": "228.475",
      "weeklyRange": "4.675",
      "sectionBreak": false,
      "dailyTarget": "1.775",
      "nextDailyTarget": "2.375",
      "dailyAchievement": "215.5%",
      "weeklyTarget": "",
      "nextWeeklyTarget": "",
      "weeklyAchievement": "",
      "impliedVolTrend": "",
      "underTargetStreak": 0,
      "weeklyUnderTargetStreak": 0,
      "weeklyTrend": ""
    },
    {
      "date": "2026-01-29",
      "dailyHigh": "233.15",
      "dailyLow": "231.025",
      "dailyRange": "2.125",
      "fullAchievement": "2.225",
      "historicVol": "12.3%",
      "impliedVol": "",
      "weeklyHigh": "233.15",
      "weeklyLow": "229.575",
      "weeklyRange": "3.575",
      "sectionBreak": false,
      "dailyTarget": "1.65",
      "nextDailyTarget": "1.775",
      "dailyAchievement": "128.8%",
      "weeklyTarget": "",
      "nextWeeklyTarget": "",
      "weeklyAchievement": "",
      "impliedVolTrend": "",
      "underTargetStreak": 0,
      "weeklyUnderTargetStreak": 0,
      "weeklyTrend": ""
    },
    {
      "date": "2026-01-28",
      "dailyHigh": "232.575",
      "dailyLow": "229.575",
      "dailyRange": "3",
      "fullAchievement": "2.05",
      "historicVol": "11.3%",
      "impliedVol": "",
      "weeklyHigh": "232.575",
      "weeklyLow": "229.575",
      "weeklyRange": "3",
      "sectionBreak": false,
      "dailyTarget": "2.05",
      "nextDailyTarget": "1.65",
      "dailyAchievement": "146.3%",
      "weeklyTarget": "",
      "nextWeeklyTarget": "",
      "weeklyAchievement": "",
      "impliedVolTrend": "",
      "underTargetStreak": 0,
      "weeklyUnderTargetStreak": 0,
      "weeklyTrend": ""
    },
    {
      "date": "2026-01-27",
      "dailyHigh": "231.5",
      "dailyLow": "229.95",
      "dailyRange": "1.55",
      "fullAchievement": "2.55",
      "historicVol": "14.1%",
      "impliedVol": "",
      "weeklyHigh": "231.5",
      "weeklyLow": "229.9",
      "weeklyRange": "1.6",
      "sectionBreak": false,
      "dailyTarget": "1.95",
      "nextDailyTarget": "2.05",
      "dailyAchievement": "79.5%",
      "weeklyTarget": "",
      "nextWeeklyTarget": "",
      "weeklyAchievement": "",
      "impliedVolTrend": "",
      "underTargetStreak": 2,
      "weeklyUnderTargetStreak": 0,
      "weeklyTrend": ""
    },
    {
      "date": "2026-01-26",
      "dailyHigh": "231.5",
      "dailyLow": "229.9",
      "dailyRange": "1.6",
      "fullAchievement": "2.425",
      "historicVol": "13.4%",
      "impliedVol": "",
      "weeklyHigh": "231.5",
      "weeklyLow": "229.9",
      "weeklyRange": "1.6",
      "sectionBreak": true,
      "dailyTarget": "2.075",
      "nextDailyTarget": "1.95",
      "dailyAchievement": "77.1%",
      "weeklyTarget": "",
      "nextWeeklyTarget": "",
      "weeklyAchievement": "",
      "impliedVolTrend": "",
      "underTargetStreak": 1,
      "weeklyUnderTargetStreak": 0,
      "weeklyTrend": ""
    },
    {
      "date": "2026-01-23",
      "dailyHigh": "231.375",
      "dailyLow": "226.9",
      "dailyRange": "4.475",
      "fullAchievement": "2.6",
      "historicVol": "14.5%",
      "impliedVol": "",
      "weeklyHigh": "231.375",
      "weeklyLow": "226.9",
      "weeklyRange": "4.475",
      "sectionBreak": false,
      "dailyTarget": "",
      "nextDailyTarget": "2.075",
      "dailyAchievement": "",
      "weeklyTarget": "",
      "nextWeeklyTarget": "",
      "weeklyAchievement": "",
      "impliedVolTrend": "",
      "underTargetStreak": 0,
      "weeklyUnderTargetStreak": 0,
      "weeklyTrend": ""
    },
    {
      "date": "2026-01-22",
      "dailyHigh": "229.55",
      "dailyLow": "228.375",
      "dailyRange": "1.175",
      "fullAchievement": "",
      "historicVol": "",
      "impliedVol": "",
      "weeklyHigh": "229.55",
      "weeklyLow": "227",
      "weeklyRange": "2.55",
      "sectionBreak": false,
      "dailyTarget": "",
      "nextDailyTarget": "",
      "dailyAchievement": "",
      "weeklyTarget": "",
      "nextWeeklyTarget": "",
      "weeklyAchievement": "",
      "impliedVolTrend": "",
      "underTargetStreak": 0,
      "weeklyUnderTargetStreak": 0,
      "weeklyTrend": ""
    },
    {
      "date": "2026-01-21",
      "dailyHigh": "229.175",
      "dailyLow": "227",
      "dailyRange": "2.175",
      "fullAchievement": "",
      "historicVol": "",
      "impliedVol": "",
      "weeklyHigh": "229.175",
      "weeklyLow": "227",
      "weeklyRange": "2.175",
      "sectionBreak": false,
      "dailyTarget": "",
      "nextDailyTarget": "",
      "dailyAchievement": "",
      "weeklyTarget": "",
      "nextWeeklyTarget": "",
      "weeklyAchievement": "",
      "impliedVolTrend": "",
      "underTargetStreak": 0,
      "weeklyUnderTargetStreak": 0,
      "weeklyTrend": ""
    }
  ]
}