{
  "symbol": "ZCN26",
  "commodity": "Corn",
  "month": "Jul",
  "updatedAt": "2026-04-13T12:50:45.819237-05:00",
  "rows": [
    {
      "date": "2026-04-13",
      "dailyHigh": "456",
      "dailyLow": "451.75",
      "dailyClose": 452.75,
      "dailyRange": "4.25",
      "fullAchievement": "6.5",
      "nextDailyTarget": "5.25",
      "historicVol": "18.4%",
      "impliedVol": "",
      "weeklyHigh": "465.75",
      "weeklyLow": "448.5",
      "weeklyRange": "17.25",
      "weeklyFullAchievement": "17.25",
      "nextWeeklyTarget": "13.75",
      "sectionBreak": false,
      "dailyTarget": "5.5",
      "dailyAchievement": "77.3%",
      "weeklyTarget": "14.75",
      "weeklyAchievement": "116.9%"
    },
    {
      "date": "2026-04-10",
      "dailyHigh": "456.5",
      "dailyLow": "448.5",
      "dailyClose": 451.25,
      "dailyRange": "8",
      "fullAchievement": "7",
      "nextDailyTarget": "5.5",
      "historicVol": "19.9%",
      "impliedVol": "",
      "weeklyHigh": "465.75",
      "weeklyLow": "448.5",
      "weeklyRange": "17.25",
      "weeklyFullAchievement": "18.5",
      "nextWeeklyTarget": "14.75",
      "sectionBreak": true,
      "dailyTarget": "5.25",
      "dailyAchievement": "152.4%",
      "weeklyTarget": "15.25",
      "weeklyAchievement": "113.1%"
    },
    {
      "date": "2026-04-09",
      "dailyHigh": "460.5",
      "dailyLow": "453.25",
      "dailyClose": 455.0,
      "dailyRange": "7.25",
      "fullAchievement": "6.5",
      "nextDailyTarget": "5.25",
      "historicVol": "18.3%",
      "impliedVol": "",
      "weeklyHigh": "471.5",
      "weeklyLow": "452.75",
      "weeklyRange": "18.75",
      "weeklyFullAchievement": "19",
      "nextWeeklyTarget": "15.25",
      "sectionBreak": false,
      "dailyTarget": "4.75",
      "dailyAchievement": "152.6%",
      "weeklyTarget": "15.5",
      "weeklyAchievement": "121.0%"
    },
    {
      "date": "2026-04-08",
      "dailyHigh": "458.5",
      "dailyLow": "452.75",
      "dailyClose": 458.0,
      "dailyRange": "5.75",
      "fullAchievement": "6",
      "nextDailyTarget": "4.75",
      "historicVol": "16.8%",
      "impliedVol": "",
      "weeklyHigh": "471.5",
      "weeklyLow": "452.75",
      "weeklyRange": "18.75",
      "weeklyFullAchievement": "19.5",
      "nextWeeklyTarget": "15.5",
      "sectionBreak": false,
      "dailyTarget": "5.75",
      "dailyAchievement": "100.0%",
      "weeklyTarget": "13.5",
      "weeklyAchievement": "138.9%"
    },
    {
      "date": "2026-04-07",
      "dailyHigh": "465.75",
      "dailyLow": "459.25",
      "dailyClose": 460.0,
      "dailyRange": "6.5",
      "fullAchievement": "7.25",
      "nextDailyTarget": "5.75",
      "historicVol": "19.9%",
      "impliedVol": "",
      "weeklyHigh": "472.75",
      "weeklyLow": "459.25",
      "weeklyRange": "13.5",
      "weeklyFullAchievement": "17",
      "nextWeeklyTarget": "13.5",
      "sectionBreak": false,
      "dailyTarget": "7",
      "dailyAchievement": "92.9%",
      "weeklyTarget": "14.5",
      "weeklyAchievement": "93.1%"
    },
    {
      "date": "2026-04-06",
      "dailyHigh": "465.5",
      "dailyLow": "459.75",
      "dailyClose": 465.25,
      "dailyRange": "5.75",
      "fullAchievement": "8.75",
      "nextDailyTarget": "7",
      "historicVol": "24.3%",
      "impliedVol": "",
      "weeklyHigh": "477.5",
      "weeklyLow": "459.25",
      "weeklyRange": "18.25",
      "weeklyFullAchievement": "18.25",
      "nextWeeklyTarget": "14.5",
      "sectionBreak": false,
      "dailyTarget": "8.25",
      "dailyAchievement": "69.7%",
      "weeklyTarget": "15.5",
      "weeklyAchievement": "117.7%"
    },
    {
      "date": "2026-04-02",
      "dailyHigh": "471.5",
      "dailyLow": "462.25",
      "dailyClose": 463.25,
      "dailyRange": "9.25",
      "fullAchievement": "10.25",
      "nextDailyTarget": "8.25",
      "historicVol": "28.6%",
      "impliedVol": "",
      "weeklyHigh": "481.25",
      "weeklyLow": "459.25",
      "weeklyRange": "22",
      "weeklyFullAchievement": "19.5",
      "nextWeeklyTarget": "15.5",
      "sectionBreak": true,
      "dailyTarget": "8.5",
      "dailyAchievement": "108.8%",
      "weeklyTarget": "15.5",
      "weeklyAchievement": "141.9%"
    },
    {
      "date": "2026-04-01",
      "dailyHigh": "470.75",
      "dailyLow": "459.25",
      "dailyClose": 465.0,
      "dailyRange": "11.5",
      "fullAchievement": "10.75",
      "nextDailyTarget": "8.5",
      "historicVol": "29.8%",
      "impliedVol": "",
      "weeklyHigh": "481.25",
      "weeklyLow": "459.25",
      "weeklyRange": "22",
      "weeklyFullAchievement": "19.5",
      "nextWeeklyTarget": "15.5",
      "sectionBreak": false,
      "dailyTarget": "8",
      "dailyAchievement": "143.8%",
      "weeklyTarget": "15.75",
      "weeklyAchievement": "139.7%"
    },
    {
      "date": "2026-03-31",
      "dailyHigh": "472.75",
      "dailyLow": "462.5",
      "dailyClose": 468.25,
      "dailyRange": "10.25",
      "fullAchievement": "10",
      "nextDailyTarget": "8",
      "historicVol": "27.3%",
      "impliedVol": "",
      "weeklyHigh": "481.25",
      "weeklyLow": "462.5",
      "weeklyRange": "18.75",
      "weeklyFullAchievement": "19.75",
      "nextWeeklyTarget": "15.75",
      "sectionBreak": false,
      "dailyTarget": "6.75",
      "dailyAchievement": "151.9%",
      "weeklyTarget": "16.5",
      "weeklyAchievement": "113.6%"
    },
    {
      "date": "2026-03-30",
      "dailyHigh": "477.5",
      "dailyLow": "466.75",
      "dailyClose": 467.5,
      "dailyRange": "10.75",
      "fullAchievement": "8.5",
      "nextDailyTarget": "6.75",
      "historicVol": "23.5%",
      "impliedVol": "",
      "weeklyHigh": "481.25",
      "weeklyLow": "466.75",
      "weeklyRange": "14.5",
      "weeklyFullAchievement": "20.5",
      "nextWeeklyTarget": "16.5",
      "sectionBreak": false,
      "dailyTarget": "6.75",
      "dailyAchievement": "159.3%",
      "weeklyTarget": "17.75",
      "weeklyAchievement": "81.7%"
    },
    {
      "date": "2026-03-27",
      "dailyHigh": "481.25",
      "dailyLow": "472.25",
      "dailyClose": 473.5,
      "dailyRange": "9",
      "fullAchievement": "8.5",
      "nextDailyTarget": "6.75",
      "historicVol": "22.8%",
      "impliedVol": "",
      "weeklyHigh": "484",
      "weeklyLow": "467.5",
      "weeklyRange": "16.5",
      "weeklyFullAchievement": "22.25",
      "nextWeeklyTarget": "17.75",
      "sectionBreak": true,
      "dailyTarget": "6",
      "dailyAchievement": "150.0%",
      "weeklyTarget": "17.75",
      "weeklyAchievement": "93.0%"
    },
    {
      "date": "2026-03-26",
      "dailyHigh": "479.25",
      "dailyLow": "473.25",
      "dailyClose": 478.0,
      "dailyRange": "6",
      "fullAchievement": "7.5",
      "nextDailyTarget": "6",
      "historicVol": "20.1%",
      "impliedVol": "",
      "weeklyHigh": "484",
      "weeklyLow": "467.5",
      "weeklyRange": "16.5",
      "weeklyFullAchievement": "22.25",
      "nextWeeklyTarget": "17.75",
      "sectionBreak": false,
      "dailyTarget": "8.75",
      "dailyAchievement": "68.6%",
      "weeklyTarget": "19",
      "weeklyAchievement": "86.8%"
    },
    {
      "date": "2026-03-25",
      "dailyHigh": "478.5",
      "dailyLow": "468.25",
      "dailyClose": 477.75,
      "dailyRange": "10.25",
      "fullAchievement": "11",
      "nextDailyTarget": "8.75",
      "historicVol": "29.5%",
      "impliedVol": "",
      "weeklyHigh": "484",
      "weeklyLow": "467.5",
      "weeklyRange": "16.5",
      "weeklyFullAchievement": "23.75",
      "nextWeeklyTarget": "19",
      "sectionBreak": false,
      "dailyTarget": "7.5",
      "dailyAchievement": "136.7%",
      "weeklyTarget": "20.75",
      "weeklyAchievement": "79.5%"
    },
    {
      "date": "2026-03-24",
      "dailyHigh": "475.75",
      "dailyLow": "469.5",
      "dailyClose": 472.5,
      "dailyRange": "6.25",
      "fullAchievement": "9.25",
      "nextDailyTarget": "7.5",
      "historicVol": "25.1%",
      "impliedVol": "",
      "weeklyHigh": "484",
      "weeklyLow": "463.25",
      "weeklyRange": "20.75",
      "weeklyFullAchievement": "26",
      "nextWeeklyTarget": "20.75",
      "sectionBreak": false,
      "dailyTarget": "7.5",
      "dailyAchievement": "83.3%",
      "weeklyTarget": "22.5",
      "weeklyAchievement": "92.2%"
    },
    {
      "date": "2026-03-23",
      "dailyHigh": "484",
      "dailyLow": "467.5",
      "dailyClose": 470.5,
      "dailyRange": "16.5",
      "fullAchievement": "9.25",
      "nextDailyTarget": "7.5",
      "historicVol": "25.4%",
      "impliedVol": "",
      "weeklyHigh": "484",
      "weeklyLow": "461",
      "weeklyRange": "23",
      "weeklyFullAchievement": "28",
      "nextWeeklyTarget": "22.5",
      "sectionBreak": false,
      "dailyTarget": "6.5",
      "dailyAchievement": "253.8%",
      "weeklyTarget": "19",
      "weeklyAchievement": "121.1%"
    },
    {
      "date": "2026-03-20",
      "dailyHigh": "479.5",
      "dailyLow": "474.5",
      "dailyClose": 476.0,
      "dailyRange": "5",
      "fullAchievement": "8",
      "nextDailyTarget": "6.5",
      "historicVol": "21.7%",
      "impliedVol": "",
      "weeklyHigh": "480.75",
      "weeklyLow": "461",
      "weeklyRange": "19.75",
      "weeklyFullAchievement": "23.75",
      "nextWeeklyTarget": "19",
      "sectionBreak": true,
      "dailyTarget": "7.5",
      "dailyAchievement": "66.7%",
      "weeklyTarget": "17",
      "weeklyAchievement": "116.2%"
    },
    {
      "date": "2026-03-19",
      "dailyHigh": "480.75",
      "dailyLow": "474.25",
      "dailyClose": 480.0,
      "dailyRange": "6.5",
      "fullAchievement": "9.5",
      "nextDailyTarget": "7.5",
      "historicVol": "25.6%",
      "impliedVol": "",
      "weeklyHigh": "480.75",
      "weeklyLow": "461",
      "weeklyRange": "19.75",
      "weeklyFullAchievement": "21.25",
      "nextWeeklyTarget": "17",
      "sectionBreak": false,
      "dailyTarget": "9.5",
      "dailyAchievement": "68.4%",
      "weeklyTarget": "17.75",
      "weeklyAchievement": "111.3%"
    },
    {
      "date": "2026-03-18",
      "dailyHigh": "476",
      "dailyLow": "463.25",
      "dailyClose": 474.5,
      "dailyRange": "12.75",
      "fullAchievement": "11.75",
      "nextDailyTarget": "9.5",
      "historicVol": "31.7%",
      "impliedVol": "",
      "weeklyHigh": "480.75",
      "weeklyLow": "461",
      "weeklyRange": "19.75",
      "weeklyFullAchievement": "22.25",
      "nextWeeklyTarget": "17.75",
      "sectionBreak": false,
      "dailyTarget": "8.5",
      "dailyAchievement": "150.0%",
      "weeklyTarget": "19",
      "weeklyAchievement": "103.9%"
    },
    {
      "date": "2026-03-17",
      "dailyHigh": "470.5",
      "dailyLow": "461",
      "dailyClose": 465.5,
      "dailyRange": "9.5",
      "fullAchievement": "10.5",
      "nextDailyTarget": "8.5",
      "historicVol": "28.6%",
      "impliedVol": "",
      "weeklyHigh": "480.75",
      "weeklyLow": "461",
      "weeklyRange": "19.75",
      "weeklyFullAchievement": "23.75",
      "nextWeeklyTarget": "19",
      "sectionBreak": false,
      "dailyTarget": "8",
      "dailyAchievement": "118.8%",
      "weeklyTarget": "20",
      "weeklyAchievement": "98.8%"
    },
    {
      "date": "2026-03-16",
      "dailyHigh": "477",
      "dailyLow": "464",
      "dailyClose": 465.75,
      "dailyRange": "13",
      "fullAchievement": "10",
      "nextDailyTarget": "8",
      "historicVol": "27.3%",
      "impliedVol": "",
      "weeklyHigh": "480.75",
      "weeklyLow": "457",
      "weeklyRange": "23.75",
      "weeklyFullAchievement": "25",
      "nextWeeklyTarget": "20",
      "sectionBreak": false,
      "dailyTarget": "7.25",
      "dailyAchievement": "179.3%",
      "weeklyTarget": "16.75",
      "weeklyAchievement": "141.8%"
    },
    {
      "date": "2026-03-13",
      "dailyHigh": "478.75",
      "dailyLow": "470",
      "dailyClose": 478.25,
      "dailyRange": "8.75",
      "fullAchievement": "9",
      "nextDailyTarget": "7.25",
      "historicVol": "24.3%",
      "impliedVol": "",
      "weeklyHigh": "487.5",
      "weeklyLow": "457",
      "weeklyRange": "30.5",
      "weeklyFullAchievement": "21",
      "nextWeeklyTarget": "16.75",
      "sectionBreak": true,
      "dailyTarget": "7",
      "dailyAchievement": "125.0%",
      "weeklyTarget": "14.5",
      "weeklyAchievement": "210.3%"
    },
    {
      "date": "2026-03-12",
      "dailyHigh": "480.75",
      "dailyLow": "472.75",
      "dailyClose": 474.0,
      "dailyRange": "8",
      "fullAchievement": "8.75",
      "nextDailyTarget": "7",
      "historicVol": "23.6%",
      "impliedVol": "",
      "weeklyHigh": "487.5",
      "weeklyLow": "457",
      "weeklyRange": "30.5",
      "weeklyFullAchievement": "18",
      "nextWeeklyTarget": "14.5",
      "sectionBreak": false,
      "dailyTarget": "10.75",
      "dailyAchievement": "74.4%",
      "weeklyTarget": "15.5",
      "weeklyAchievement": "196.8%"
    },
    {
      "date": "2026-03-11",
      "dailyHigh": "473.25",
      "dailyLow": "462.75",
      "dailyClose": 472.0,
      "dailyRange": "10.5",
      "fullAchievement": "13.5",
      "nextDailyTarget": "10.75",
      "historicVol": "36.8%",
      "impliedVol": "",
      "weeklyHigh": "487.5",
      "weeklyLow": "452.5",
      "weeklyRange": "35",
      "weeklyFullAchievement": "19.25",
      "nextWeeklyTarget": "15.5",
      "sectionBreak": false,
      "dailyTarget": "10.75",
      "dailyAchievement": "97.7%",
      "weeklyTarget": "16.5",
      "weeklyAchievement": "212.1%"
    },
    {
      "date": "2026-03-10",
      "dailyHigh": "464.75",
      "dailyLow": "457",
      "dailyClose": 463.25,
      "dailyRange": "7.75",
      "fullAchievement": "13.5",
      "nextDailyTarget": "10.75",
      "historicVol": "37.1%",
      "impliedVol": "",
      "weeklyHigh": "487.5",
      "weeklyLow": "450.25",
      "weeklyRange": "37.25",
      "weeklyFullAchievement": "20.75",
      "nextWeeklyTarget": "16.5",
      "sectionBreak": false,
      "dailyTarget": "11.5",
      "dailyAchievement": "67.4%",
      "weeklyTarget": "16.5",
      "weeklyAchievement": "225.8%"
    },
    {
      "date": "2026-03-09",
      "dailyHigh": "487.5",
      "dailyLow": "465",
      "dailyClose": 465.5,
      "dailyRange": "22.5",
      "fullAchievement": "14.5",
      "nextDailyTarget": "11.5",
      "historicVol": "39.9%",
      "impliedVol": "",
      "weeklyHigh": "487.5",
      "weeklyLow": "450.25",
      "weeklyRange": "37.25",
      "weeklyFullAchievement": "20.75",
      "nextWeeklyTarget": "16.5",
      "sectionBreak": false,
      "dailyTarget": "7.25",
      "dailyAchievement": "310.3%",
      "weeklyTarget": "10.75",
      "weeklyAchievement": "346.5%"
    },
    {
      "date": "2026-03-06",
      "dailyHigh": "471.5",
      "dailyLow": "461.5",
      "dailyClose": 471.0,
      "dailyRange": "10",
      "fullAchievement": "9",
      "nextDailyTarget": "7.25",
      "historicVol": "24.5%",
      "impliedVol": "",
      "weeklyHigh": "471.5",
      "weeklyLow": "450.25",
      "weeklyRange": "21.25",
      "weeklyFullAchievement": "13.5",
      "nextWeeklyTarget": "10.75",
      "sectionBreak": true,
      "dailyTarget": "6.5",
      "dailyAchievement": "153.8%",
      "weeklyTarget": "8.5",
      "weeklyAchievement": "250.0%"
    },
    {
      "date": "2026-03-05",
      "dailyHigh": "463.5",
      "dailyLow": "452.5",
      "dailyClose": 462.75,
      "dailyRange": "11",
      "fullAchievement": "8",
      "nextDailyTarget": "6.5",
      "historicVol": "22.1%",
      "impliedVol": "",
      "weeklyHigh": "463.5",
      "weeklyLow": "450",
      "weeklyRange": "13.5",
      "weeklyFullAchievement": "10.5",
      "nextWeeklyTarget": "8.5",
      "sectionBreak": false,
      "dailyTarget": "5.5",
      "dailyAchievement": "200.0%",
      "weeklyTarget": "8.5",
      "weeklyAchievement": "158.8%"
    },
    {
      "date": "2026-03-04",
      "dailyHigh": "456.25",
      "dailyLow": "450.25",
      "dailyClose": 453.5,
      "dailyRange": "6",
      "fullAchievement": "7",
      "nextDailyTarget": "5.5",
      "historicVol": "19.8%",
      "impliedVol": "",
      "weeklyHigh": "460.5",
      "weeklyLow": "448.5",
      "weeklyRange": "12",
      "weeklyFullAchievement": "10.5",
      "nextWeeklyTarget": "8.5",
      "sectionBreak": false,
      "dailyTarget": "5.75",
      "dailyAchievement": "104.3%",
      "weeklyTarget": "9",
      "weeklyAchievement": "133.3%"
    },
    {
      "date": "2026-03-03",
      "dailyHigh": "460.5",
      "dailyLow": "453.5",
      "dailyClose": 455.5,
      "dailyRange": "7",
      "fullAchievement": "7.25",
      "nextDailyTarget": "5.75",
      "historicVol": "20.6%",
      "impliedVol": "",
      "weeklyHigh": "460.5",
      "weeklyLow": "446.5",
      "weeklyRange": "14",
      "weeklyFullAchievement": "11.25",
      "nextWeeklyTarget": "9",
      "sectionBreak": false,
      "dailyTarget": "5.5",
      "dailyAchievement": "127.3%",
      "weeklyTarget": "9",
      "weeklyAchievement": "155.6%"
    },
    {
      "date": "2026-03-02",
      "dailyHigh": "460",
      "dailyLow": "452",
      "dailyClose": 454.25,
      "dailyRange": "8",
      "fullAchievement": "6.75",
      "nextDailyTarget": "5.5",
      "historicVol": "18.8%",
      "impliedVol": "",
      "weeklyHigh": "460",
      "weeklyLow": "446",
      "weeklyRange": "14",
      "weeklyFullAchievement": "11.25",
      "nextWeeklyTarget": "9",
      "sectionBreak": false,
      "dailyTarget": "4.5",
      "dailyAchievement": "177.8%",
      "weeklyTarget": "7.5",
      "weeklyAchievement": "186.7%"
    },
    {
      "date": "2026-02-27",
      "dailyHigh": "457",
      "dailyLow": "450",
      "dailyClose": 456.0,
      "dailyRange": "7",
      "fullAchievement": "5.5",
      "nextDailyTarget": "4.5",
      "historicVol": "15.2%",
      "impliedVol": "",
      "weeklyHigh": "457",
      "weeklyLow": "446",
      "weeklyRange": "11",
      "weeklyFullAchievement": "9.25",
      "nextWeeklyTarget": "7.5",
      "sectionBreak": true,
      "dailyTarget": "3.5",
      "dailyAchievement": "200.0%",
      "weeklyTarget": "7.5",
      "weeklyAchievement": "146.7%"
    },
    {
      "date": "2026-02-26",
      "dailyHigh": "453.5",
      "dailyLow": "448.5",
      "dailyClose": 451.25,
      "dailyRange": "5",
      "fullAchievement": "4.25",
      "nextDailyTarget": "3.5",
      "historicVol": "11.8%",
      "impliedVol": "",
      "weeklyHigh": "453.5",
      "weeklyLow": "443.5",
      "weeklyRange": "10",
      "weeklyFullAchievement": "9.25",
      "nextWeeklyTarget": "7.5",
      "sectionBreak": false,
      "dailyTarget": "3.75",
      "dailyAchievement": "133.3%",
      "weeklyTarget": "8",
      "weeklyAchievement": "125.0%"
    },
    {
      "date": "2026-02-25",
      "dailyHigh": "450.75",
      "dailyLow": "446.5",
      "dailyClose": 450.25,
      "dailyRange": "4.25",
      "fullAchievement": "4.75",
      "nextDailyTarget": "3.75",
      "historicVol": "13.7%",
      "impliedVol": "",
      "weeklyHigh": "453.25",
      "weeklyLow": "442.25",
      "weeklyRange": "11",
      "weeklyFullAchievement": "10",
      "nextWeeklyTarget": "8",
      "sectionBreak": false,
      "dailyTarget": "4.25",
      "dailyAchievement": "100.0%",
      "weeklyTarget": "8",
      "weeklyAchievement": "137.5%"
    },
    {
      "date": "2026-02-24",
      "dailyHigh": "449.25",
      "dailyLow": "446",
      "dailyClose": 447.5,
      "dailyRange": "3.25",
      "fullAchievement": "5.25",
      "nextDailyTarget": "4.25",
      "historicVol": "14.8%",
      "impliedVol": "",
      "weeklyHigh": "453.25",
      "weeklyLow": "442.25",
      "weeklyRange": "11",
      "weeklyFullAchievement": "10",
      "nextWeeklyTarget": "8",
      "sectionBreak": false,
      "dailyTarget": "4.25",
      "dailyAchievement": "76.5%",
      "weeklyTarget": "8.5",
      "weeklyAchievement": "129.4%"
    },
    {
      "date": "2026-02-23",
      "dailyHigh": "453.25",
      "dailyLow": "446.25",
      "dailyClose": 448.75,
      "dailyRange": "7",
      "fullAchievement": "5.25",
      "nextDailyTarget": "4.25",
      "historicVol": "14.7%",
      "impliedVol": "",
      "weeklyHigh": "453.25",
      "weeklyLow": "442.25",
      "weeklyRange": "11",
      "weeklyFullAchievement": "10.5",
      "nextWeeklyTarget": "8.5",
      "sectionBreak": false,
      "dailyTarget": "3",
      "dailyAchievement": "233.3%",
      "weeklyTarget": "7.5",
      "weeklyAchievement": "146.7%"
    },
    {
      "date": "2026-02-20",
      "dailyHigh": "448.75",
      "dailyLow": "443.5",
      "dailyClose": 448.25,
      "dailyRange": "5.25",
      "fullAchievement": "3.75",
      "nextDailyTarget": "3",
      "historicVol": "10.9%",
      "impliedVol": "",
      "weeklyHigh": "450.5",
      "weeklyLow": "442.25",
      "weeklyRange": "8.25",
      "weeklyFullAchievement": "9.5",
      "nextWeeklyTarget": "7.5",
      "sectionBreak": true,
      "dailyTarget": "3.25",
      "dailyAchievement": "161.5%",
      "weeklyTarget": "7.5",
      "weeklyAchievement": "110.0%"
    },
    {
      "date": "2026-02-19",
      "dailyHigh": "445.5",
      "dailyLow": "442.25",
      "dailyClose": 444.5,
      "dailyRange": "3.25",
      "fullAchievement": "4",
      "nextDailyTarget": "3.25",
      "historicVol": "11.3%",
      "impliedVol": "",
      "weeklyHigh": "450.5",
      "weeklyLow": "442.25",
      "weeklyRange": "8.25",
      "weeklyFullAchievement": "9.25",
      "nextWeeklyTarget": "7.5",
      "sectionBreak": false,
      "dailyTarget": "3.25",
      "dailyAchievement": "100.0%",
      "weeklyTarget": "7.75",
      "weeklyAchievement": "106.5%"
    },
    {
      "date": "2026-02-18",
      "dailyHigh": "446.25",
      "dailyLow": "443.25",
      "dailyClose": 444.75,
      "dailyRange": "3",
      "fullAchievement": "4",
      "nextDailyTarget": "3.25",
      "historicVol": "11.3%",
      "impliedVol": "",
      "weeklyHigh": "450.5",
      "weeklyLow": "441.75",
      "weeklyRange": "8.75",
      "weeklyFullAchievement": "9.75",
      "nextWeeklyTarget": "7.75",
      "sectionBreak": false,
      "dailyTarget": "3.75",
      "dailyAchievement": "80.0%",
      "weeklyTarget": "7.75",
      "weeklyAchievement": "112.9%"
    },
    {
      "date": "2026-02-17",
      "dailyHigh": "449",
      "dailyLow": "443.5",
      "dailyClose": 444.25,
      "dailyRange": "5.5",
      "fullAchievement": "4.75",
      "nextDailyTarget": "3.75",
      "historicVol": "13.7%",
      "impliedVol": "",
      "weeklyHigh": "450.5",
      "weeklyLow": "441.75",
      "weeklyRange": "8.75",
      "weeklyFullAchievement": "9.75",
      "nextWeeklyTarget": "7.75",
      "sectionBreak": false,
      "dailyTarget": "3.5",
      "dailyAchievement": "157.1%",
      "weeklyTarget": "7.75",
      "weeklyAchievement": "112.9%"
    },
    {
      "date": "2026-02-13",
      "dailyHigh": "450.5",
      "dailyLow": "447.25",
      "dailyClose": 450.0,
      "dailyRange": "3.25",
      "fullAchievement": "4.25",
      "nextDailyTarget": "3.5",
      "historicVol": "12.1%",
      "impliedVol": "",
      "weeklyHigh": "450.5",
      "weeklyLow": "441.75",
      "weeklyRange": "8.75",
      "weeklyFullAchievement": "9.75",
      "nextWeeklyTarget": "7.75",
      "sectionBreak": true,
      "dailyTarget": "3.5",
      "dailyAchievement": "92.9%",
      "weeklyTarget": "8.25",
      "weeklyAchievement": "106.1%"
    },
    {
      "date": "2026-02-12",
      "dailyHigh": "449.75",
      "dailyLow": "444.25",
      "dailyClose": 449.75,
      "dailyRange": "5.5",
      "fullAchievement": "4.25",
      "nextDailyTarget": "3.5",
      "historicVol": "11.9%",
      "impliedVol": "",
      "weeklyHigh": "450.25",
      "weeklyLow": "441.75",
      "weeklyRange": "8.5",
      "weeklyFullAchievement": "10.25",
      "nextWeeklyTarget": "8.25",
      "sectionBreak": false,
      "dailyTarget": "2.5",
      "dailyAchievement": "220.0%",
      "weeklyTarget": "7.75",
      "weeklyAchievement": "109.7%"
    },
    {
      "date": "2026-02-11",
      "dailyHigh": "445.75",
      "dailyLow": "441.75",
      "dailyClose": 444.25,
      "dailyRange": "4",
      "fullAchievement": "3.25",
      "nextDailyTarget": "2.5",
      "historicVol": "9.6%",
      "impliedVol": "",
      "weeklyHigh": "450.25",
      "weeklyLow": "441",
      "weeklyRange": "9.25",
      "weeklyFullAchievement": "9.75",
      "nextWeeklyTarget": "7.75",
      "sectionBreak": false,
      "dailyTarget": "3.25",
      "dailyAchievement": "123.1%",
      "weeklyTarget": "7.75",
      "weeklyAchievement": "119.4%"
    },
    {
      "date": "2026-02-10",
      "dailyHigh": "445.75",
      "dailyLow": "442.75",
      "dailyClose": 444.75,
      "dailyRange": "3",
      "fullAchievement": "4",
      "nextDailyTarget": "3.25",
      "historicVol": "11.8%",
      "impliedVol": "",
      "weeklyHigh": "450.25",
      "weeklyLow": "439.75",
      "weeklyRange": "10.5",
      "weeklyFullAchievement": "9.75",
      "nextWeeklyTarget": "7.75",
      "sectionBreak": false,
      "dailyTarget": "4.75",
      "dailyAchievement": "63.2%",
      "weeklyTarget": "7.75",
      "weeklyAchievement": "135.5%"
    },
    {
      "date": "2026-02-09",
      "dailyHigh": "445",
      "dailyLow": "442",
      "dailyClose": 443.75,
      "dailyRange": "3",
      "fullAchievement": "6",
      "nextDailyTarget": "4.75",
      "historicVol": "17.3%",
      "impliedVol": "",
      "weeklyHigh": "450.25",
      "weeklyLow": "439.75",
      "weeklyRange": "10.5",
      "weeklyFullAchievement": "9.75",
      "nextWeeklyTarget": "7.75",
      "sectionBreak": false,
      "dailyTarget": "5.75",
      "dailyAchievement": "52.2%",
      "weeklyTarget": "8.5",
      "weeklyAchievement": "123.5%"
    },
    {
      "date": "2026-02-06",
      "dailyHigh": "450.25",
      "dailyLow": "444",
      "dailyClose": 445.25,
      "dailyRange": "6.25",
      "fullAchievement": "7.25",
      "nextDailyTarget": "5.75",
      "historicVol": "21.1%",
      "impliedVol": "",
      "weeklyHigh": "450.25",
      "weeklyLow": "438.25",
      "weeklyRange": "12",
      "weeklyFullAchievement": "10.5",
      "nextWeeklyTarget": "8.5",
      "sectionBreak": true,
      "dailyTarget": "5",
      "dailyAchievement": "125.0%",
      "weeklyTarget": "8.25",
      "weeklyAchievement": "145.5%"
    },
    {
      "date": "2026-02-05",
      "dailyHigh": "449.75",
      "dailyLow": "441",
      "dailyClose": 449.25,
      "dailyRange": "8.75",
      "fullAchievement": "6.25",
      "nextDailyTarget": "5",
      "historicVol": "17.8%",
      "impliedVol": "",
      "weeklyHigh": "449.75",
      "weeklyLow": "438.25",
      "weeklyRange": "11.5",
      "weeklyFullAchievement": "10.25",
      "nextWeeklyTarget": "8.25",
      "sectionBreak": false,
      "dailyTarget": "3.75",
      "dailyAchievement": "233.3%",
      "weeklyTarget": "7.5",
      "weeklyAchievement": "153.3%"
    },
    {
      "date": "2026-02-04",
      "dailyHigh": "446.75",
      "dailyLow": "439.75",
      "dailyClose": 443.25,
      "dailyRange": "7",
      "fullAchievement": "4.75",
      "nextDailyTarget": "3.75",
      "historicVol": "14.0%",
      "impliedVol": "",
      "weeklyHigh": "448.25",
      "weeklyLow": "438.25",
      "weeklyRange": "10",
      "weeklyFullAchievement": "9.5",
      "nextWeeklyTarget": "7.5",
      "sectionBreak": false,
      "dailyTarget": "3.5",
      "dailyAchievement": "200.0%",
      "weeklyTarget": "6.5",
      "weeklyAchievement": "153.8%"
    },
    {
      "date": "2026-02-03",
      "dailyHigh": "442.75",
      "dailyLow": "439.75",
      "dailyClose": 442.0,
      "dailyRange": "3",
      "fullAchievement": "4.5",
      "nextDailyTarget": "3.5",
      "historicVol": "13.3%",
      "impliedVol": "",
      "weeklyHigh": "448.25",
      "weeklyLow": "438.25",
      "weeklyRange": "10",
      "weeklyFullAchievement": "8.25",
      "nextWeeklyTarget": "6.5",
      "sectionBreak": false,
      "dailyTarget": "4",
      "dailyAchievement": "75.0%",
      "weeklyTarget": "",
      "weeklyAchievement": ""
    },
    {
      "date": "2026-02-02",
      "dailyHigh": "442.75",
      "dailyLow": "438.25",
      "dailyClose": 439.75,
      "dailyRange": "4.5",
      "fullAchievement": "5",
      "nextDailyTarget": "4",
      "historicVol": "14.8%",
      "impliedVol": "",
      "weeklyHigh": "448.25",
      "weeklyLow": "438.25",
      "weeklyRange": "10",
      "weeklyFullAchievement": "",
      "nextWeeklyTarget": "",
      "sectionBreak": false,
      "dailyTarget": "4.25",
      "dailyAchievement": "105.9%",
      "weeklyTarget": "",
      "weeklyAchievement": ""
    },
    {
      "date": "2026-01-30",
      "dailyHigh": "446.25",
      "dailyLow": "440",
      "dailyClose": 442.0,
      "dailyRange": "6.25",
      "fullAchievement": "5.25",
      "nextDailyTarget": "4.25",
      "historicVol": "15.4%",
      "impliedVol": "",
      "weeklyHigh": "448.25",
      "weeklyLow": "440",
      "weeklyRange": "8.25",
      "weeklyFullAchievement": "",
      "nextWeeklyTarget": "",
      "sectionBreak": true,
      "dailyTarget": "3.5",
      "dailyAchievement": "178.6%",
      "weeklyTarget": "",
      "weeklyAchievement": ""
    },
    {
      "date": "2026-01-29",
      "dailyHigh": "448.25",
      "dailyLow": "443.75",
      "dailyClose": 445.75,
      "dailyRange": "4.5",
      "fullAchievement": "4.5",
      "nextDailyTarget": "3.5",
      "historicVol": "12.7%",
      "impliedVol": "",
      "weeklyHigh": "448.25",
      "weeklyLow": "437.5",
      "weeklyRange": "10.75",
      "weeklyFullAchievement": "",
      "nextWeeklyTarget": "",
      "sectionBreak": false,
      "dailyTarget": "3.25",
      "dailyAchievement": "138.5%",
      "weeklyTarget": "",
      "weeklyAchievement": ""
    },
    {
      "date": "2026-01-28",
      "dailyHigh": "446.25",
      "dailyLow": "441",
      "dailyClose": 444.0,
      "dailyRange": "5.25",
      "fullAchievement": "4",
      "nextDailyTarget": "3.25",
      "historicVol": "11.8%",
      "impliedVol": "",
      "weeklyHigh": "446.25",
      "weeklyLow": "436",
      "weeklyRange": "10.25",
      "weeklyFullAchievement": "",
      "nextWeeklyTarget": "",
      "sectionBreak": false,
      "dailyTarget": "3.75",
      "dailyAchievement": "140.0%",
      "weeklyTarget": "",
      "weeklyAchievement": ""
    },
    {
      "date": "2026-01-27",
      "dailyHigh": "444",
      "dailyLow": "440.5",
      "dailyClose": 440.75,
      "dailyRange": "3.5",
      "fullAchievement": "4.75",
      "nextDailyTarget": "3.75",
      "historicVol": "13.6%",
      "impliedVol": "",
      "weeklyHigh": "444.75",
      "weeklyLow": "436",
      "weeklyRange": "8.75",
      "weeklyFullAchievement": "",
      "nextWeeklyTarget": "",
      "sectionBreak": false,
      "dailyTarget": "3.5",
      "dailyAchievement": "100.0%",
      "weeklyTarget": "",
      "weeklyAchievement": ""
    },
    {
      "date": "2026-01-26",
      "dailyHigh": "444.75",
      "dailyLow": "441.25",
      "dailyClose": 442.0,
      "dailyRange": "3.5",
      "fullAchievement": "4.5",
      "nextDailyTarget": "3.5",
      "historicVol": "12.8%",
      "impliedVol": "",
      "weeklyHigh": "444.75",
      "weeklyLow": "436",
      "weeklyRange": "8.75",
      "weeklyFullAchievement": "",
      "nextWeeklyTarget": "",
      "sectionBreak": false,
      "dailyTarget": "4.25",
      "dailyAchievement": "82.4%",
      "weeklyTarget": "",
      "weeklyAchievement": ""
    },
    {
      "date": "2026-01-23",
      "dailyHigh": "444.5",
      "dailyLow": "437.5",
      "dailyClose": 443.75,
      "dailyRange": "7",
      "fullAchievement": "5.25",
      "nextDailyTarget": "4.25",
      "historicVol": "14.9%",
      "impliedVol": "",
      "weeklyHigh": "444.5",
      "weeklyLow": "433.5",
      "weeklyRange": "11",
      "weeklyFullAchievement": "",
      "nextWeeklyTarget": "",
      "sectionBreak": true,
      "dailyTarget": "3.25",
      "dailyAchievement": "215.4%",
      "weeklyTarget": "",
      "weeklyAchievement": ""
    },
    {
      "date": "2026-01-22",
      "dailyHigh": "438.75",
      "dailyLow": "436",
      "dailyClose": 438.5,
      "dailyRange": "2.75",
      "fullAchievement": "4",
      "nextDailyTarget": "3.25",
      "historicVol": "11.4%",
      "impliedVol": "",
      "weeklyHigh": "441.75",
      "weeklyLow": "433.5",
      "weeklyRange": "8.25",
      "weeklyFullAchievement": "",
      "nextWeeklyTarget": "",
      "sectionBreak": false,
      "dailyTarget": "4",
      "dailyAchievement": "68.8%",
      "weeklyTarget": "",
      "weeklyAchievement": ""
    },
    {
      "date": "2026-01-21",
      "dailyHigh": "441.75",
      "dailyLow": "436",
      "dailyClose": 436.25,
      "dailyRange": "5.75",
      "fullAchievement": "5",
      "nextDailyTarget": "4",
      "historicVol": "14.9%",
      "impliedVol": "",
      "weeklyHigh": "441.75",
      "weeklyLow": "433.5",
      "weeklyRange": "8.25",
      "weeklyFullAchievement": "",
      "nextWeeklyTarget": "",
      "sectionBreak": false,
      "dailyTarget": "4",
      "dailyAchievement": "143.8%",
      "weeklyTarget": "",
      "weeklyAchievement": ""
    },
    {
      "date": "2026-01-20",
      "dailyHigh": "439.5",
      "dailyLow": "436.25",
      "dailyClose": 437.75,
      "dailyRange": "3.25",
      "fullAchievement": "5",
      "nextDailyTarget": "4",
      "historicVol": "14.4%",
      "impliedVol": "",
      "weeklyHigh": "439.75",
      "weeklyLow": "433.5",
      "weeklyRange": "6.25",
      "weeklyFullAchievement": "",
      "nextWeeklyTarget": "",
      "sectionBreak": false,
      "dailyTarget": "4.5",
      "dailyAchievement": "72.2%",
      "weeklyTarget": "",
      "weeklyAchievement": ""
    },
    {
      "date": "2026-01-16",
      "dailyHigh": "439.75",
      "dailyLow": "433.5",
      "dailyClose": 438.0,
      "dailyRange": "6.25",
      "fullAchievement": "5.5",
      "nextDailyTarget": "4.5",
      "historicVol": "16.1%",
      "impliedVol": "",
      "weeklyHigh": "",
      "weeklyLow": "",
      "weeklyRange": "",
      "weeklyFullAchievement": "",
      "nextWeeklyTarget": "",
      "sectionBreak": true,
      "dailyTarget": "4",
      "dailyAchievement": "156.2%",
      "weeklyTarget": "",
      "weeklyAchievement": ""
    },
    {
      "date": "2026-01-15",
      "dailyHigh": "438.75",
      "dailyLow": "433.5",
      "dailyClose": 434.0,
      "dailyRange": "5.25",
      "fullAchievement": "5",
      "nextDailyTarget": "4",
      "historicVol": "14.7%",
      "impliedVol": "",
      "weeklyHigh": "",
      "weeklyLow": "",
      "weeklyRange": "",
      "weeklyFullAchievement": "",
      "nextWeeklyTarget": "",
      "sectionBreak": false,
      "dailyTarget": "",
      "dailyAchievement": "",
      "weeklyTarget": "",
      "weeklyAchievement": ""
    },
    {
      "date": "2026-01-14",
      "dailyHigh": "439",
      "dailyLow": "434",
      "dailyClose": 436.0,
      "dailyRange": "5",
      "fullAchievement": "",
      "nextDailyTarget": "",
      "historicVol": "",
      "impliedVol": "",
      "weeklyHigh": "",
      "weeklyLow": "",
      "weeklyRange": "",
      "weeklyFullAchievement": "",
      "nextWeeklyTarget": "",
      "sectionBreak": false,
      "dailyTarget": "",
      "dailyAchievement": "",
      "weeklyTarget": "",
      "weeklyAchievement": ""
    },
    {
      "date": "2026-01-13",
      "dailyHigh": "438.5",
      "dailyLow": "433.75",
      "dailyClose": 434.5,
      "dailyRange": "4.75",
      "fullAchievement": "",
      "nextDailyTarget": "",
      "historicVol": "",
      "impliedVol": "",
      "weeklyHigh": "",
      "weeklyLow": "",
      "weeklyRange": "",
      "weeklyFullAchievement": "",
      "nextWeeklyTarget": "",
      "sectionBreak": false,
      "dailyTarget": "",
      "dailyAchievement": "",
      "weeklyTarget": "",
      "weeklyAchievement": ""
    }
  ]
}